Workbook
Name NativeTimeline_Data: #N/A

Sheet Planilha2
A1: Data | B1: Profissional | C1: Unidade | D1: Leads | E1: Consultas | F1: Consultas Online | G1: Retornos | H1: Retornos Online | I1: Cirurgias | J1: Cirurgias realizadas no CC | K1: Valor dos Serviços
A2: 44316 | B2: Gabriel Oliveira | C2: São José dos Campos | I2: 11 | J2: 1
A3: 44316 | C3: São José dos Campos | K3: 146850

Sheet Relatório
A7: 'Unidade | B7: 'Leads | C7: 'Consultas | D7: 'Consultas Online | E7: 'Taxa Conversão Consultas x Leads | F7: 'Retornos | G7: 'Retornos Online | H7: '% Retornos x Consultas | I7: 'Cirurgias | J7: 'Taxa Conversão Cirurgias x Consultas | K7: 'Valor dos Serviços | L7: 'Valor Médio dos Serviços
A8: Campinas | B8: 1125 | C8: 95 | D8: 22 | E8: 0.104 | F8: 88 | G8: 12 | H8: 0.46082949 | I8: 58 | J8: 0.4957265 | K8: 866232 | L8: 14935.034
A9: Jundiaí | B9: 546 | C9: 39 | D9: 3 | E9: 0.076923077 | F9: 32 | G9: 0 | H9: 0.43243243 | I9: 21 | J9: 0.5 | K9: 318260 | L9: 15155.238
A10: Piracicaba | B10: 421 | C10: 35 | D10: 6 | E10: 0.097387173 | F10: 24 | G10: 0 | H10: 0.36923077 | I10: 17 | J10: 0.41463415 | K10: 256000 | L10: 15058.824
A11: Ribeirão Preto | B11: 1071 | C11: 74 | D11: 0 | E11: 0.069094304 | F11: 79 | G11: 0 | H11: 0.51633987 | I11: 68 | J11: 0.91891892 | K11: 1139700 | L11: 16760.294
A12: Sorocaba | B12: 446 | C12: 45 | D12: 4 | E12: 0.10986547 | F12: 45 | G12: 3 | H12: 0.49484536 | I12: 32 | J12: 0.65306122 | K12: 472593 | L12: 14768.531
A13: Total Geral | B13: 3609 | C13: 288 | D13: 35 | E13: 0.089498476 | F13: 268 | G13: 15 | H13: 0.4669967 | I13: 196 | J13: 0.60681115 | K13: 3052785 | L13: 15575.434

Sheet Base Dados
A1: Data | B1: Profissional | C1: Unidade | D1: Leads | E1: Consultas | F1: Consultas Online | G1: Retornos | H1: Retornos Online | I1: Cirurgias | J1: Valor dos Serviços | K1: Coluna1
A2: 44227 | B2: Leticia Ambrosano | C2: Campinas | E2: 45 | F2: 2 | G2: 55 | H2: 0 | I2: 19
A3: 44227 | B3: Carolina Guimarães | C3: Goiânia | E3: 18 | F3: 3 | G3: 13 | I3: 9
A4: 44227 | B4: Erika Freire | C4: Belo Horizonte | E4: 16 | F4: 2 | G4: 24 | H4: 10 | I4: 15
A5: 44227 | B5: Frederico Gontijo | C5: Anália Franco | E5: 19 | F5: 2 | G5: 13 | I5: 8
A6: 44227 | B6: Frederico Gontijo | C6: Itaim Bibi | E6: 9 | F6: 2 | G6: 11 | H6: 2 | I6: 8
A7: 44227 | B7: Gabriel Oliveira | C7: São José dos Campos | E7: 49 | F7: 7 | G7: 34 | H7: 0 | I7: 10
A8: 44227 | B8: Gabriel Oliveira | C8: Guarulhos | E8: 31 | F8: 0 | G8: 16 | H8: 2 | I8: 6
A9: 44227 | B9: Harielle Asega | C9: Curitiba | E9: 44 | F9: 13 | G9: 4 | H9: 0 | I9: 3
A10: 44227 | B10: Isaura Fasciani | C10: ABC | E10: 70 | F10: 1 | G10: 59 | H10: 3 | I10: 11
A11: 44227 | B11: Leonardo Almeida | C11: Belo Horizonte | E11: 19 | F11: 10 | G11: 20 | H11: 6 | I11: 9
A12: 44227 | B12: Leonardo Andrade | C12: Itaim Bibi | E12: 27 | F12: 2 | G12: 38 | H12: 5 | I12: 19
A13: 44227 | B13: Leticia Pinheiro | C13: Goiânia | E13: 27 | F13: 3 | G13: 19 | I13: 10
A14: 44227 | B14: Natalia Medeiros | C14: Brasília | E14: 32 | F14: 5 | G14: 3 | H14: 0 | I14: 5
A15: 44227 | B15: Suellen Oliveira | C15: Anália Franco | E15: 28 | F15: 0 | G15: 10 | I15: 12
A16: 44227 | B16: Suellen Oliveira | C16: Guarulhos | E16: 15 | F16: 2 | G16: 4 | H16: 0 | I16: 4
A17: 44227 | B17: Taiane Terra | C17: Brasília | E17: 34 | F17: 6 | G17: 13 | H17: 0 | I17: 10
A18: 44227 | B18: Thaiana Botarelli | C18: Campinas | E18: 25 | F18: 3 | G18: 12 | H18: 0 | I18: 7
A19: 44227 | B19: Thaiana Botarelli | C19: Sorocaba | E19: 26 | F19: 20 | G19: 25 | H19: 0 | I19: 11
A20: 44227 | B20: Arthur Basile | C20: Ribeirão Preto | E20: 53 | F20: 0 | G20: 37 | H20: 0 | I20: 27
A21: 44227 | C21: Anália Franco | D21: 517 | J21: 276150
A22: 44227 | C22: ABC | D22: 340 | J22: 151850
A23: 44227 | C23: Itaim Bibi | D23: 713 | J23: 384750
A24: 44227 | C24: Guarulhos | D24: 299 | J24: =14000+14450+14450+13000+13000+13000+14450+12000+14450+13000 -> 135800
A25: 44227 | C25: Ribeirão Preto | D25: 438 | J25: =14450+14000+14450+13500+14450+14450+15000+14450+14000+15500+14000+14450+14000+14000+14000+14000+14450+15900+15900+14000+6000+14450+15000+15900+14450+14000+14450 -> 383200
A26: 44227 | C26: Sorocaba | D26: 277 | J26: 164500
A27: 44227 | C27: Campinas | D27: 672 | J27: 315400
A28: 44227 | C28: São José dos Campos | D28: 251 | J28: 141500
A29: 44227 | C29: Brasília | D29: 360 | J29: 199950
A30: 44227 | C30: Curitiba | D30: 436 | J30: 43400
A31: 44227 | C31: Belo Horizonte | D31: 1000 | J31: 340100
A32: 44227 | C32: Goiânia | D32: 412 | J32: 244000
A33: 44255 | B33: Leticia Ambrosano | C33: Campinas | E33: 47 | F33: 8 | G33: 52 | H33: 2 | I33: 22
A34: 44255 | B34: Thaiana Botarelli | C34: Campinas | E34: 32 | F34: 8 | G34: 23 | H34: 0 | I34: 4
A35: 44255 | B35: Thaiana Botarelli | C35: Sorocaba | E35: 52 | F35: 16 | G35: 18 | H35: 0 | I35: 10
A36: 44255 | B36: Erika Freire | C36: Belo Horizonte | E36: 19 | F36: 3 | G36: 24 | H36: 12 | I36: 12
A37: 44255 | B37: Leonardo Almeida | C37: Belo Horizonte | E37: 7 | F37: 3 | G37: 7 | H37: 6 | I37: 10
A38: 44255 | B38: Gabriel Oliveira | C38: São José dos Campos | E38: 34 | F38: 8 | G38: 26 | H38: 0 | I38: 11
A39: 44255 | B39: Gabriel Oliveira | C39: Guarulhos | E39: 26 | F39: 0 | G39: 11 | H39: 1 | I39: 6
A40: 44255 | B40: Suellen Oliveira | C40: Guarulhos | E40: 21 | F40: 17 | G40: 6 | H40: 1 | I40: 7
A41: 44255 | B41: Suellen Oliveira | C41: Anália Franco | E41: 0 | F41: 0 | G41: 13 | I41: 8
A42: 44255 | B42: Frederico Gontijo | C42: Anália Franco | E42: 82 | F42: 11 | G42: 21 | I42: 12
A43: 44255 | B43: Frederico Gontijo | C43: Itaim Bibi | E43: 7 | F43: 0 | G43: 5 | H43: 0 | I43: 2
A44: 44255 | B44: Leonardo Andrade | C44: Itaim Bibi | E44: 61 | F44: 9 | G44: 63 | H44: 8 | I44: 17
A45: 44255 | B45: Natalia Medeiros | C45: Brasília | E45: 42 | F45: 5 | G45: 6 | H45: 0 | I45: 6
A46: 44255 | B46: Taiane Terra | C46: Brasília | E46: 29 | F46: 1 | G46: 7 | H46: 0 | I46: 10
A47: 44255 | B47: Leticia Pinheiro | C47: Goiânia | E47: 9 | F47: 8 | G47: 19 | I47: 11
A48: 44255 | B48: Carolina Guimarães | C48: Goiânia | E48: 19 | F48: 1 | G48: 16 | I48: 8
A49: 44255 | B49: Arthur Basile | C49: Ribeirão Preto | E49: 56 | F49: 0 | G49: 30 | H49: 0 | I49: 22
A50: 44255 | B50: Isaura Fasciani | C50: ABC | E50: 31 | F50: 2 | G50: 55 | H50: 2 | I50: 11
A51: 44255 | B51: Harielle Asega | C51: Curitiba | E51: 16 | F51: 3 | G51: 25 | H51: 11 | I51: 19
A52: 44255 | C52: Anália Franco | D52: 473 | J52: 280960
A53: 44255 | C53: ABC | D53: 320 | J53: 151800
A54: 44255 | C54: Itaim Bibi | D54: 858 | J54: 265800
A55: 44255 | C55: Guarulhos | D55: 360 | J55: =14450+14450+14000+14450+14000+13000+12000+14450+14450+14000+14450+14450+13000 -> 181150
A56: 44255 | C56: Ribeirão Preto | D56: 460 | J56: 323450
A57: 44255 | C57: Sorocaba | D57: 223 | J57: 128700
A58: 44255 | C58: Campinas | D58: 646 | J58: 340250
A59: 44255 | C59: São José dos Campos | D59: 282 | J59: =14450+13500+14000+13000+12000+12000+13000+12500+13000+12500+13500 -> 143450
A60: 44255 | C60: Brasília | D60: 500 | J60: 203300
A61: 44255 | C61: Curitiba | D61: 413 | J61: 249750
A62: 44255 | C62: Belo Horizonte | D62: 1007 | J62: =15900+14450+13000+13000+13500+13500+13500+14800+14150+13000+14450+14450+15900+14450+12500+13000+13000+12500+13000+14000+12500+13000 -> 301550
A63: 44255 | C63: Goiânia | D63: 461 | J63: 238000
A64: 44286 | B64: Leticia Ambrosano | C64: Campinas | E64: 37 | F64: 30 | G64: 30 | H64: 3 | I64: 21
A65: 44286 | B65: Thaiana Botarelli | C65: Campinas | E65: 20 | F65: 22 | G65: 12 | H65: 0 | I65: 15
A66: 44286 | B66: Thaiana Botarelli | C66: Sorocaba | E66: 30 | F66: 18 | G66: 32 | H66: 6 | I66: 9
A67: 44286 | B67: Erika Freire | C67: Belo Horizonte | E67: 16 | F67: 26 | G67: 42 | H67: 30 | I67: 17
A68: 44286 | B68: Leonardo Almeida | C68: Belo Horizonte | E68: 45 | F68: 39 | G68: 14 | H68: 12 | I68: 13
A69: 44286 | B69: Gabriel Oliveira | C69: São José dos Campos | E69: 54 | F69: 11 | G69: 34 | H69: 2 | I69: 14
A70: 44286 | B70: Gabriel Oliveira | C70: Guarulhos | E70: 23 | F70: 9 | G70: 20 | I70: 5
A71: 44286 | B71: Suellen Oliveira | C71: Guarulhos | E71: 33 | F71: 17 | G71: 16 | H71: 2 | I71: 5
A72: 44286 | B72: Suellen Oliveira | C72: Anália Franco | E72: 0 | F72: 0 | G72: 12 | I72: 3
A73: 44286 | B73: Frederico Gontijo | C73: Anália Franco | E73: 58 | F73: 14 | G73: 31 | I73: 19
A74: 44286 | B74: Frederico Gontijo | C74: Itaim Bibi | E74: 3 | F74: 0 | G74: 3 | I74: 5
A75: 44286 | B75: Leonardo Andrade | C75: Itaim Bibi | E75: 60 | F75: 20 | G75: 60 | H75: 17 | I75: 21
A76: 44286 | B76: Haline Pires | C76: Itaim Bibi | E76: 70 | F76: 39 | G76: 1 | H76: 0 | I76: 0
A77: 44286 | B77: Natalia Medeiros | C77: Brasília | E77: 23 | F77: 8 | G77: 6 | H77: 1 | I77: 8
A78: 44286 | B78: Taiane Terra | C78: Brasília | E78: 54 | F78: 7 | G78: 11 | H78: 2 | I78: 12
A79: 44286 | B79: Leticia Pinheiro | C79: Goiânia | E79: 40 | F79: 15 | G79: 18 | I79: 9
A80: 44286 | B80: Carolina Guimarães | C80: Goiânia | E80: 12 | F80: 8 | G80: 20 | I80: 11
A81: 44286 | B81: Arthur Basile | C81: Ribeirão Preto | E81: 46 | F81: 0 | G81: 22 | H81: 0 | I81: 23
A82: 44286 | B82: Isaura Fasciani | C82: ABC | E82: 0 | F82: 0 | G82: 11 | H82: 0 | I82: 0
A83: 44286 | B83: Larissa Crestani | C83: ABC | E83: 73 | F83: 4 | G83: 24 | H83: 0 | I83: 17
A84: 44286 | B84: Harielle Asega | C84: Curitiba | E84: 22 | F84: 15 | G84: 9 | H84: 8 | I84: 15
A85: 44286 | C85: Anália Franco | D85: 448 | J85: 272950
A86: 44286 | C86: ABC | D86: 358 | J86: 246640
A87: 44286 | C87: Itaim Bibi | D87: 804 | J87: 379050
A88: 44286 | C88: Guarulhos | D88: 517 | J88: =14000+14450+12000+14450+14450+12000+14450+13900+12000+14450 -> 136150
A89: 44286 | C89: Ribeirão Preto | D89: 448 | J89: 308150
A90: 44286 | C90: Sorocaba | D90: 283 | J90: 114950
A91: 44286 | C91: Campinas | D91: 615 | J91: 483250
A92: 44286 | C92: São José dos Campos | D92: 321 | J92: 197415
A93: 44286 | C93: Brasília | D93: 463 | J93: 280000
A94: 44286 | C94: Curitiba | D94: 438 | J94: =13000+14450+12000+13000+13000+13000+14450+15900+14450+13000+15900+14500+13000+12000+15900 -> 207550
A95: 44286 | C95: Belo Horizonte | D95: 823 | J95: 399450
A96: 44286 | C96: Goiânia | D96: 437 | J96: =13000+13000+12000+14000+12000+13000+13000+13000+13000+13000+13000+13000+13000+13000+12000+13000+14000+13000+13000+13000 -> 259000
A97: 44316 | B97: Leticia Ambrosano | C97: Campinas | E97: 59 | F97: 15 | G97: 49 | H97: 6 | I97: 26
A98: 44316 | B98: Thaiana Botarelli | C98: Campinas | E98: 22 | F98: 6 | G98: 28 | H98: 1 | I98: 8
A99: 44316 | B99: Thaiana Botarelli | C99: Sorocaba | E99: 53 | F99: 6 | G99: 23 | H99: 4 | I99: 11
A100: 44316 | B100: Erika Freire | C100: Belo Horizonte | E100: 19 | F100: 15 | G100: 41 | H100: 9 | I100: 18
...

Sheet N° procedimentos
A2: Unidade | B2: 44562 | C2: 44593 | D2: 44621 | E2: 44652 | F2: 44682 | G2: 44713 | H2: 44743 | I2: 44774 | J2: 44805 | K2: 44835 | L2: 44866 | M2: 44896 | N2: 44927 | O2: 44958 | P2: 44986 | Q2: 45017 | R2: 45047 | S2: 45078 | T2: 45108 | U2: 45139 | V2: 45170 | W2: 45200 | X2: 45231 | Y2: 45261 | Z2: 45292 | AA2: 45323 | AB2: 45352 | AC2: 45383 | AD2: 45413 | AE2: 45444 | AF2: 45474 | AG2: 45505 | AH2: 45536 | AI2: 45566 | AJ2: 45597 | AK2: 45627 | AL2: 45658 | AM2: 45689 | AN2: 45717 | AO2: 45748 | AP2: 45778 | AQ2: 45809 | AR2: 45839 | AS2: 45870 | AT2: 45901 | AU2: 45931 | AV2: 45962 | AW2: 45992 | AX2: 46023 | AY2: 46054 | AZ2: 46082 | BA2: 46113 | BB2: 46143
A3: ABC | B3: 19 | C3: 10 | D3: 12 | E3: 10 | F3: 11 | G3: 10 | H3: 16 | I3: 15 | J3: 15 | K3: 15 | L3: 13 | M3: 7 | N3: 18 | O3: 11 | P3: 10 | Q3: 13 | R3: 19 | S3: 16 | T3: 17 | U3: 16 | V3: 16 | W3: 14 | X3: 11 | Y3: 10 | Z3: 15 | AA3: 12 | AB3: 10 | AC3: 10 | AD3: 5 | AE3: 6 | AF3: 11 | AG3: 9 | AH3: 8 | AI3: 8 | AJ3: 6 | AK3: 9 | AL3: 11 | AM3: 10 | AN3: 10 | AO3: 15 | AP3: 8 | AQ3: 3 | AR3: 12 | AS3: 16 | AT3: 10 | AU3: 12 | AV3: 6 | AW3: 8 | AX3: 15 | AY3: 15 | AZ3: 8 | BA3: 10
A4: Anália Franco | B4: 15 | C4: 18 | D4: 13 | E4: 20 | F4: 10 | G4: 9 | H4: 25 | I4: 20 | J4: 15 | K4: 14 | L4: 26 | M4: 20 | N4: 17 | O4: 18 | P4: 20 | Q4: 17 | R4: 7 | S4: 16 | T4: 16 | U4: 11 | V4: 19 | W4: 15 | X4: 9 | Y4: 14 | Z4: 11 | AA4: 6 | AB4: 15 | AC4: 15 | AD4: 13 | AE4: 7 | AF4: 15 | AG4: 10 | AH4: 12 | AI4: 1 | AJ4: 7 | AK4: 10 | AL4: 6 | AM4: 7 | AN4: 9 | AO4: 11 | AP4: 10 | AQ4: 10 | AR4: 10 | AS4: 8 | AT4: 11 | AU4: 10 | AV4: 8 | AW4: 17 | AX4: 10 | AY4: 14 | AZ4: 11 | BA4: 7
A5: Belo Horizonte | B5: 35 | C5: 25 | D5: 30 | E5: 26 | F5: 34 | G5: 30 | H5: 40 | I5: 25 | J5: 26 | K5: 30 | L5: 27 | M5: 27 | N5: 38 | O5: 34 | P5: 28 | Q5: 33 | R5: 30 | S5: 31 | T5: 34 | U5: 35 | V5: 21 | W5: 35 | X5: 32 | Y5: 30 | Z5: 32 | AA5: 27 | AB5: 26 | AC5: 29 | AD5: 24 | AE5: 31 | AF5: 35 | AG5: 39 | AH5: 24 | AI5: 20 | AJ5: 33 | AK5: 26 | AL5: 40 | AM5: 22 | AN5: 25 | AO5: 22 | AP5: 29 | AQ5: 17 | AR5: 29 | AS5: 18 | AT5: 20 | AU5: 20 | AV5: 18 | AW5: 20 | AX5: 21 | AY5: 20 | AZ5: 26 | BA5: 12
A6: Brasília | B6: 35 | C6: 32 | D6: 36 | E6: 26 | F6: 23 | G6: 21 | H6: 39 | I6: 31 | J6: 23 | K6: 15 | L6: 20 | M6: 15 | N6: 31 | O6: 26 | P6: 28 | Q6: 25 | R6: 25 | S6: 25 | T6: 34 | U6: 27 | V6: 34 | W6: 35 | X6: 25 | Y6: 22 | Z6: 20 | AA6: 26 | AB6: 26 | AC6: 26 | AD6: 17 | AE6: 18 | AF6: 30 | AG6: 25 | AH6: 20 | AI6: 25 | AJ6: 15 | AK6: 25 | AL6: 30 | AM6: 25 | AN6: 15 | AO6: 27 | AP6: 15 | AQ6: 20 | AR6: 16 | AS6: 24 | AT6: 23 | AU6: 21 | AV6: 19 | AW6: 20 | AX6: 27 | AY6: 18 | AZ6: 20 | BA6: 17
A7: Campinas | B7: 36 | C7: 22 | D7: 27 | E7: 28 | F7: 50 | G7: 35 | H7: 45 | I7: 32 | J7: 31 | K7: 30 | L7: 28 | M7: 30 | N7: 40 | O7: 40 | P7: 50 | Q7: 46 | R7: 45 | S7: 46 | T7: 40 | U7: 40 | V7: 50 | W7: 50 | X7: 43 | Y7: 41 | Z7: 40 | AA7: 39 | AB7: 35 | AC7: 38 | AD7: 35 | AE7: 34 | AF7: 42 | AG7: 41 | AH7: 30 | AI7: 36 | AJ7: 28 | AK7: 28 | AL7: 31 | AM7: 32 | AN7: 22 | AO7: 19 | AP7: 23 | AQ7: 19 | AR7: 25 | AS7: 25 | AT7: 15 | AU7: 27 | AV7: 16 | AW7: 22 | AX7: 22 | AY7: 20 | AZ7: 16 | BA7: 19
A8: Curitiba | B8: 11 | C8: 12 | D8: 16 | E8: 18 | F8: 17 | G8: 14 | H8: 22 | I8: 10 | J8: 18 | K8: 13 | L8: 12 | M8: 10 | N8: 16 | O8: 16 | P8: 16 | Q8: 12 | R8: 10 | S8: 16 | T8: 19 | U8: 17 | V8: 14 | W8: 14 | X8: 8 | Y8: 8 | Z8: 6 | AA8: 12 | AB8: 11 | AC8: 5 | AD8: 6 | AE8: 7 | AF8: 11 | AG8: 12 | AH8: 2 | AI8: 10 | AJ8: 5 | AK8: 9 | AL8: 7 | AM8: 8 | AN8: 7 | AO8: 6 | AP8: 5 | AQ8: 5 | AR8: 16 | AS8: 10 | AT8: 11 | AU8: 8 | AV8: 7 | AW8: 9 | AX8: 12 | AY8: 11 | AZ8: 12 | BA8: 8
A9: Goiânia | B9: 26 | C9: 26 | D9: 30 | E9: 30 | F9: 25 | G9: 20 | H9: 20 | I9: 21 | J9: 30 | K9: 20 | L9: 20 | M9: 20 | N9: 20 | O9: 16 | P9: 12 | Q9: 15 | R9: 16 | S9: 23 | T9: 21 | U9: 17 | V9: 26 | W9: 20 | X9: 24 | Y9: 20 | Z9: 22 | AA9: 13 | AB9: 24 | AC9: 25 | AD9: 13 | AE9: 12 | AF9: 16 | AG9: 27 | AH9: 17 | AI9: 21 | AJ9: 19 | AK9: 18 | AL9: 30 | AM9: 20 | AN9: 17 | AO9: 18 | AP9: 13 | AQ9: 8 | AR9: 22 | AS9: 21 | AT9: 20 | AU9: 18 | AV9: 16 | AW9: 15 | AX9: 20 | AY9: 14 | AZ9: 13 | BA9: 16
A10: Guarulhos | B10: 22 | C10: 4 | D10: 11 | E10: 12 | F10: 11 | G10: 12 | H10: 13 | I10: 12 | J10: 11 | K10: 17 | L10: 14 | M10: 7 | N10: 10 | O10: 11 | P10: 10 | Q10: 8 | R10: 9 | S10: 11 | T10: 15 | U10: 8 | V10: 11 | W10: 9 | X10: 5 | Y10: 11 | Z10: 5 | AA10: 4 | AB10: 11 | AC10: 8 | AD10: 4 | AE10: 5 | AF10: 9 | AG10: 8 | AH10: 4 | AI10: 8 | AJ10: 8 | AK10: 4 | AL10: 11 | AM10: 5 | AN10: 11 | AO10: 11 | AP10: 2 | AQ10: 9 | AR10: 11 | AS10: 8 | AT10: 9 | AU10: 11 | AV10: 6 | AW10: 9 | AX10: 12 | AY10: 10 | AZ10: 9 | BA10: 7
A11: Ribeirão Preto | B11: 23 | C11: 26 | D11: 27 | E11: 20 | F11: 25 | G11: 25 | H11: 27 | I11: 32 | J11: 35 | K11: 34 | L11: 21 | M11: 9 | N11: 24 | O11: 27 | P11: 22 | Q11: 22 | R11: 30 | S11: 28 | T11: 31 | U11: 33 | V11: 28 | W11: 31 | X11: 24 | Y11: 22 | Z11: 31 | AA11: 25 | AB11: 22 | AC11: 29 | AD11: 20 | AE11: 24 | AF11: 34 | AG11: 30 | AH11: 25 | AI11: 32 | AJ11: 27 | AK11: 20 | AL11: 31 | AM11: 35 | AN11: 30 | AO11: 24 | AP11: 23 | AQ11: 23 | AR11: 25 | AS11: 25 | AT11: 25 | AU11: 27 | AV11: 26 | AW11: 19 | AX11: 25 | AY11: 19 | AZ11: 24
A12: São José dos Campos | B12: 22 | C12: 13 | D12: 15 | E12: 11 | F12: 12 | G12: 13 | H12: 14 | I12: 13 | J12: 15 | K12: 15 | L12: 15 | M12: 11 | N12: 20 | O12: 14 | P12: 19 | Q12: 13 | R12: 16 | S12: 20 | T12: 10 | U12: 8 | V12: 8 | W12: 15 | X12: 9 | Y12: 7 | Z12: 11 | AA12: 8 | AB12: 8 | AC12: 12 | AD12: 8 | AE12: 7 | AF12: 9 | AG12: 3 | AH12: 4 | AI12: 5 | AJ12: 6 | AK12: 12 | AL12: 8 | AM12: 13 | AN12: 11 | AO12: 15 | AP12: 12 | AQ12: 10 | AR12: 17 | AS12: 15 | AT12: 13 | AU12: 8 | AV12: 8 | AW12: 16 | AX12: 10 | AY12: 9 | AZ12: 17 | BA12: 4
A13: Sorocaba | B13: 10 | C13: 13 | D13: 12 | E13: 11 | F13: 14 | G13: 10 | H13: 10 | I13: 16 | J13: 12 | K13: 12 | L13: 10 | M13: 11 | N13: 15 | O13: 15 | P13: 16 | Q13: 10 | R13: 11 | S13: 15 | T13: 12 | U13: 13 | V13: 5 | W13: 11 | X13: 16 | Y13: 10 | Z13: 15 | AA13: 19 | AB13: 12 | AC13: 10 | AD13: 14 | AE13: 11 | AF13: 11 | AG13: 15 | AH13: 10 | AI13: 11 | AJ13: 12 | AK13: 7 | AL13: 13 | AM13: 7 | AN13: 12 | AO13: 8 | AP13: 8 | AQ13: 4 | AR13: 11 | AS13: 10 | AT13: 8 | AU13: 9 | AV13: 11 | AW13: 9 | AX13: 9 | AY13: 11 | AZ13: 12 | BA13: 6
A14: Itaim Bibi | B14: 38 | C14: 30 | D14: 31 | E14: 34 | F14: 42 | G14: 45 | H14: 43 | I14: 38 | J14: 38 | K14: 34 | L14: 28 | M14: 21 | N14: 23 | O14: 26 | P14: 36 | Q14: 25 | R14: 40 | S14: 32 | T14: 30 | U14: 32 | V14: 29 | W14: 27 | X14: 23 | Y14: 22 | Z14: 26 | AA14: 23 | AB14: 25 | AC14: 19 | AD14: 28 | AE14: 25 | AF14: 19 | AG14: 21 | AH14: 24 | AI14: 23 | AJ14: 21 | AK14: 15 | AL14: 26 | AM14: 24 | AN14: 18 | AO14: 18 | AP14: 19 | AQ14: 20 | AR14: 25 | AS14: 24 | AT14: 21 | AU14: 23 | AV14: 24 | AW14: 18 | AX14: 22 | AY14: 23 | AZ14: 32 | BA14: 11
A15: Recife | B15: 10 | C15: 9 | D15: 15 | E15: 15 | F15: 17 | G15: 13 | H15: 20 | I15: 15 | J15: 13 | K15: 11 | L15: 10 | M15: 4 | N15: 15 | O15: 5 | P15: 10 | Q15: 11 | R15: 11 | S15: 8 | T15: 15 | U15: 10 | V15: 15 | W15: 15 | X15: 5 | Y15: 9 | Z15: 10 | AA15: 8 | AB15: 8 | AC15: 5 | AD15: 7 | AE15: 4 | AF15: 10 | AG15: 10 | AH15: 10 | AI15: 10 | AJ15: 9 | AK15: 7 | AL15: 10 | AM15: 10 | AN15: 9 | AO15: 13 | AP15: 12 | AQ15: 6 | AR15: 11 | AS15: 10 | AT15: 11 | AU15: 12 | AV15: 9 | AW15: 9 | AX15: 14 | AY15: 10 | AZ15: 12 | BA15: 8 | BD15: MMP 19233 em março
A16: Salvador | B16: 8 | C16: 11 | D16: 13 | E16: 9 | F16: 7 | G16: 8 | H16: 14 | I16: 8 | J16: 12 | K16: 11 | L16: 13 | M16: 10 | N16: 10 | O16: 6 | P16: 16 | Q16: 9 | R16: 10 | S16: 9 | T16: 11 | U16: 10 | V16: 11 | W16: 11 | X16: 5 | Y16: 8 | Z16: 16 | AA16: 10 | AB16: 8 | AC16: 7 | AD16: 8 | AE16: 14 | AF16: 13 | AG16: 18 | AH16: 12 | AI16: 5 | AJ16: 10 | AK16: 9 | AL16: 20 | AM16: 4 | AN16: 8 | AO16: 7 | AP16: 10 | AQ16: 6 | AR16: 7 | AS16: 15 | AT16: 10 | AU16: 7 | AV16: 10 | AW16: 13 | AX16: 16 | AY16: 11 | AZ16: 15 | BA16: 2
A17: Porto Alegre | B17: 10 | C17: 10 | D17: 20 | E17: 11 | F17: 11 | G17: 11 | H17: 19 | I17: 20 | J17: 16 | K17: 20 | L17: 15 | M17: 12 | N17: 15 | O17: 14 | P17: 16 | Q17: 20 | R17: 15 | S17: 16 | T17: 21 | U17: 25 | V17: 16 | W17: 20 | X17: 20 | Y17: 20 | Z17: 15 | AA17: 15 | AB17: 17 | AC17: 17 | AD17: 4 | AE17: 14 | AF17: 12 | AG17: 20 | AH17: 10 | AI17: 18 | AJ17: 17 | AK17: 11 | AL17: 16 | AM17: 14 | AN17: 15 | AO17: 13 | AP17: 16 | AQ17: 16 | AR17: 15 | AS17: 15 | AT17: 10 | AU17: 14 | AV17: 16 | AW17: 10 | AX17: 16 | AY17: 11 | AZ17: 16 | BA17: 8
A18: Rio de Janeiro | B18: 6 | C18: 8 | D18: 8 | E18: 12 | F18: 13 | G18: 12 | H18: 15 | I18: 10 | J18: 10 | K18: 10 | L18: 12 | M18: 16 | N18: 16 | O18: 15 | P18: 14 | Q18: 9 | R18: 12 | S18: 11 | T18: 12 | U18: 8 | V18: 11 | W18: 16 | X18: 10 | Y18: 13 | Z18: 14 | AA18: 3 | AB18: 13 | AC18: 15 | AD18: 16 | AE18: 9 | AF18: 14 | AG18: 13 | AH18: 12 | AI18: 10 | AJ18: 16 | AK18: 3 | AL18: 11 | AM18: 10 | AN18: 10 | AO18: 8 | AP18: 8 | AQ18: 10 | AR18: 6 | AS18: 17 | AT18: 11 | AU18: 7 | AV18: 9 | AW18: 10 | AX18: 9 | AY18: 12 | AZ18: 9 | BA18: 9
A19: Fortaleza | B19: 10 | C19: 8 | D19: 10 | E19: 10 | F19: 5 | G19: 8 | H19: 11 | I19: 4 | J19: 9 | K19: 3 | L19: 7 | M19: 4 | N19: 15 | O19: 11 | P19: 11 | Q19: 8 | R19: 5 | S19: 8 | T19: 9 | U19: 9 | V19: 4 | W19: 6 | X19: 3 | Y19: 7 | Z19: 12 | AA19: 6 | AB19: 3 | AC19: 2 | AD19: 4 | AE19: 2 | AF19: 6 | AG19: 4 | AH19: 4 | AI19: 4 | AJ19: 6 | AK19: 6 | AL19: 7 | AM19: 5 | AN19: 8 | AO19: 2 | AP19: 3 | AQ19: 5 | AR19: 3 | AS19: 4 | AT19: 3 | AU19: 1 | AV19: 7 | AW19: 2 | AX19: 7 | AY19: N/A | AZ19: N/A | BA19: N/A | BB19: N/A
A20: Uberlândia | B20: 12 | C20: 10 | D20: 11 | E20: 9 | F20: 12 | G20: 7 | H20: 14 | I20: 12 | J20: 12 | K20: 16 | L20: 16 | M20: 17 | N20: 15 | O20: 15 | P20: 23 | Q20: 28 | R20: 20 | S20: 25 | T20: 26 | U20: 29 | V20: 25 | W20: 26 | X20: 26 | Y20: 20 | Z20: 25 | AA20: 24 | AB20: 24 | AC20: 11 | AD20: 10 | AE20: 13 | AF20: 15 | AG20: 10 | AH20: 13 | AI20: 13 | AJ20: 15 | AK20: 15 | AL20: 20 | AM20: 17 | AN20: 12 | AO20: 13 | AP20: 11 | AQ20: 11 | AR20: 16 | AS20: 8 | AT20: 10 | AU20: 12 | AV20: 15 | AW20: 15 | AX20: 16 | AY20: 14 | AZ20: 7 | BA20: 6
A21: Florianópolis | F21: 10 | G21: 8 | H21: 4 | I21: 15 | J21: 11 | K21: 15 | L21: 10 | M21: 9 | N21: 18 | O21: 15 | P21: 13 | Q21: 12 | R21: 15 | S21: 11 | T21: 15 | U21: 10 | V21: 13 | W21: 11 | X21: 12 | Y21: 10 | Z21: 11 | AA21: 2 | AB21: 4 | AC21: 8 | AD21: 10 | AE21: 8 | AF21: 8 | AG21: 8 | AH21: 7 | AI21: 11 | AJ21: 7 | AK21: 10 | AL21: 8 | AM21: 4 | AN21: 10 | AO21: 5 | AP21: 8 | AQ21: 4 | AR21: 10 | AS21: 8 | AT21: 6 | AU21: 6 | AV21: 10 | AW21: 9 | AX21: 2 | AY21: 5 | AZ21: 1 | BA21: 1
A22: Joinville | G22: 0 | H22: 2 | I22: 3 | J22: 0 | K22: 2 | L22: 3 | M22: 2 | N22: 0 | O22: 5 | P22: 2 | Q22: 4 | R22: 1 | S22: 8 | T22: 10 | U22: 7 | V22: 4 | W22: 1 | X22: 2 | Y22: 8 | Z22: 10 | AA22: 5 | AB22: 3 | AC22: 7 | AD22: 1 | AE22: 8 | AF22: 7 | AG22: 9 | AH22: 3 | AI22: 3 | AJ22: N/A | AK22: N/A | AL22: N/A | AM22: N/A | AN22: N/A | AO22: N/A | AP22: N/A | AQ22: N/A | AR22: N/A | AS22: N/A | AT22: N/A | AY22: N/A
A23: Jundiaí | I23: 4 | J23: 10 | K23: 11 | L23: 9 | M23: 8 | N23: 11 | O23: 4 | P23: 6 | Q23: 4 | R23: 6 | S23: 7 | T23: 6 | U23: 6 | V23: 11 | W23: 4 | X23: 9 | Y23: 7 | Z23: 13 | AA23: 10 | AB23: 10 | AC23: 10 | AD23: 7 | AE23: 7 | AF23: 6 | AG23: 9 | AH23: 4 | AI23: 10 | AJ23: 5 | AK23: 10 | AL23: 11 | AM23: 10 | AN23: 8 | AO23: 9 | AP23: 5 | AQ23: 8 | AR23: 5 | AS23: 9 | AT23: 2 | AU23: 10 | AV23: 6 | AW23: 8 | AX23: 7 | AY23: 5 | AZ23: 9 | BA23: 4
A24: Campo Grande | J24: 2 | K24: 2 | L24: 5 | M24: 8 | N24: 8 | O24: 9 | P24: 6 | Q24: 9 | R24: 6 | S24: 10 | T24: 10 | U24: 13 | V24: 6 | W24: 7 | X24: 10 | Y24: 11 | Z24: 5 | AA24: 8 | AB24: 10 | AC24: 8 | AD24: 10 | AE24: 12 | AF24: 10 | AG24: 8 | AH24: 12 | AI24: 13 | AJ24: 11 | AK24: 10 | AL24: 10 | AM24: 11 | AN24: 9 | AO24: 10 | AP24: 10 | AQ24: 10 | AR24: 9 | AS24: 9 | AT24: 7 | AU24: 8 | AV24: 7 | AW24: 10 | AX24: 11 | AY24: 8 | AZ24: 10 | BA24: 5
A25: Manaus | N25: 2 | O25: 4 | P25: 6 | Q25: 4 | R25: 1 | S25: 4 | T25: 7 | U25: 3 | V25: 10 | W25: 3 | X25: 1 | Y25: 4 | Z25: 10 | AA25: 2 | AB25: 7 | AC25: 5 | AD25: 4 | AE25: 5 | AF25: 6 | AG25: 0 | AH25: 6 | AI25: 7 | AJ25: 8 | AK25: 8 | AL25: 4 | AM25: 3 | AN25: 5 | AO25: 4 | AP25: 2 | AQ25: 4 | AR25: 6 | AS25: N/A | AT25: N/A | AY25: N/A
A26: João Pessoa | O26: 1 | P26: 2 | Q26: 4 | R26: 4 | S26: 2 | T26: 1 | U26: 3 | V26: 2 | W26: 0 | X26: 1 | Y26: 1 | Z26: 3 | AA26: 2 | AB26: 3 | AC26: 2 | AD26: 1 | AE26: N/A | AF26: N/A | AG26: N/A | AH26: N/A | AI26: N/A | AJ26: N/A | AK26: N/A | AL26: N/A | AM26: N/A | AN26: N/A | AO26: N/A | AP26: N/A | AQ26: N/A | AR26: N/A | AS26: N/A | AT26: N/A | AY26: N/A
A27: Barra-RJ | O27: N/A | P27: 3 | Q27: 4 | R27: 3 | S27: 4 | T27: 6 | U27: 7 | V27: 2 | W27: 3 | X27: 6 | Y27: 4 | Z27: 1 | AA27: 4 | AB27: 2 | AC27: 6 | AD27: 4 | AE27: 3 | AF27: 7 | AG27: 6 | AH27: 5 | AI27: 6 | AJ27: 4 | AK27: 6 | AL27: 7 | AM27: 3 | AN27: 5 | AO27: 1 | AP27: 0 | AQ27: 1 | AR27: 2 | AS27: N/A | AT27: N/A | AY27: N/A
A28: Vitória | O28: N/A | P28: N/A | Q28: 4 | R28: 5 | S28: 2 | T28: 4 | U28: 6 | V28: 10 | W28: 8 | X28: 8 | Y28: 5 | Z28: 3 | AA28: 3 | AB28: 6 | AC28: 8 | AD28: 3 | AE28: 1 | AF28: 4 | AG28: 12 | AH28: 8 | AI28: 1 | AJ28: N/A | AK28: N/A | AL28: N/A | AM28: N/A | AN28: N/A | AO28: N/A | AP28: N/A | AQ28: N/A | AR28: N/A | AS28: N/A | AT28: N/A | AY28: N/A
A29: Santos | O29: N/A | P29: N/A | Q29: 7 | R29: 10 | S29: 4 | T29: 11 | U29: 3 | V29: 3 | W29: 5 | X29: 6 | Y29: 4 | Z29: 8 | AA29: 10 | AB29: 10 | AC29: 10 | AD29: 10 | AE29: 13 | AF29: 15 | AG29: 10 | AH29: 11 | AI29: 10 | AJ29: 10 | AK29: 8 | AL29: 11 | AM29: 11 | AN29: 11 | AO29: 8 | AP29: 10 | AQ29: 11 | AR29: 16 | AS29: 11 | AT29: 14 | AU29: 15 | AV29: 15 | AW29: 5 | AX29: 8 | AY29: 10 | AZ29: 7 | BA29: 6
A30: São Luís | O30: N/A | P30: N/A | R30: 0 | S30: 2 | T30: 1 | U30: 3 | V30: 3 | W30: 2 | X30: 10 | Y30: 1 | Z30: 5 | AA30: 3 | AB30: 1 | AC30: 8 | AD30: 2 | AE30: 2 | AF30: 4 | AG30: 5 | AH30: 0 | AI30: 4 | AJ30: 2 | AK30: 3 | AL30: N/A | AM30: N/A | AN30: N/A | AO30: N/A | AP30: N/A | AQ30: N/A | AR30: N/A | AS30: N/A | AT30: N/A | AY30: N/A
A31: Londrina | O31: N/A | P31: N/A | T31: 1 | U31: 4 | V31: 6 | W31: 3 | X31: 1 | Y31: 3 | Z31: 2 | AA31: 5 | AB31: 2 | AC31: 4 | AD31: 5 | AE31: 5 | AF31: 5 | AG31: 1 | AH31: N/A | AI31: N/A | AJ31: N/A | AK31: N/A | AL31: N/A | AM31: N/A | AN31: N/A | AO31: N/A | AP31: N/A | AQ31: N/A | AR31: N/A | AS31: N/A | AT31: N/A | AY31: N/A
A32: Cuiabá | O32: N/A | P32: N/A | X32: 0 | Y32: 1 | Z32: 1 | AA32: 4 | AB32: 3 | AC32: 4 | AD32: 5 | AE32: 2 | AF32: 4 | AG32: 4 | AH32: 2 | AI32: 2 | AJ32: 2 | AK32: 5 | AL32: 5 | AM32: N/A | AN32: N/A | AO32: N/A | AP32: N/A | AQ32: N/A | AR32: N/A | AS32: N/A | AT32: N/A | AY32: N/A
A33: Piracicaba | O33: N/A | P33: N/A | Y33: 0 | Z33: 3 | AA33: 1 | AB33: 2 | AC33: 2 | AD33: 2 | AE33: 6 | AF33: 10 | AG33: 7 | AH33: 6 | AI33: 9 | AJ33: 6 | AK33: 4 | AL33: 8 | AM33: 6 | AN33: 8 | AO33: 11 | AP33: 5 | AQ33: 5 | AR33: 8 | AS33: 2 | AT33: 3 | AU33: 2 | AV33: 6 | AW33: 7 | AX33: 5 | AY33: 6 | AZ33: 6 | BA33: 7
A34: Total | B34: =SUM(B3:B28) -> 348 | C34: =SUM(C3:C28) -> 287 | D34: =SUM(D3:D28) -> 337 | E34: =SUM(E3:E28) -> 312 | F34: =SUM(F3:F28) -> 349 | G34: =SUM(G3:G28) -> 311 | H34: =SUM(H3:H28) -> 413 | I34: =SUM(I3:I28) -> 356 | ... O34: =SUM(O3:O28) -> 358 | P34: =SUM(P3:P29) -> 395 | Q34: =SUM(Q3:Q33) -> 376 | R34: =SUM(R3:R29) -> 382 | S34: =SUM(S3:S33) -> 410 | T34: =SUM(T3:T29) -> 443 | U34: =SUM(U3:U33) -> 413 | V34: =SUM(V3:V33) -> 413 | W34: =SUM(W3:W33) -> 417 | X34: =SUM(X3:X33) -> 364 | Y34: =SUM(Y3:Y29) -> 348 | Z34: =SUM(Z3:Z33) -> 401 | AA34: =SUM(AA3:AA33) -> 339 | AB34: =SUM(AB3:AB29) -> 353 | AC34: =SUM(AC3:AC33) -> 365 | AD34: =SUM(AD3:AD33) -> 300 | AE34: =SUM(AE3:AE33) -> 315 | AF34: =SUM(AF3:AF33) -> 398 | AG34: =SUM(AG3:AG33) -> 394 | AH34: =SUM(AH3:AH33) -> 305 | AI34: =SUM(AI3:AI33) -> 336 | AJ34: =SUM(AJ3:AJ33) -> 315 | ... BB34: =SUM(BB3:BB33) -> 0
BE42: Unidade | BF42: JAN | BG42: FEV | BH42: MAR | BI42: ABR
BE43: Campinas | BF43: 22 | BG43: 20 | BH43: 16 | BI43: 18
BE44: Sorocaba | BF44: 9 | BG44: 11 | BH44: 12 | BI44: 7
BE45: Jundiaí | BF45: 7 | BG45: 5 | BH45: 9 | BI45: 4
BE46: Piracicaba | BF46: 5 | BG46: 6 | BH46: 6 | BI46: 8
BE47: TOTAL | BF47: =SUM(BF43:BF46) -> 43 | BG47: =SUM(BG43:BG46) -> 42 | BH47: =SUM(BH43:BH46) -> 43 | BI47: =SUM(BI43:BI46) -> 37

Sheet % Notas fiscais
A2: 2025 | F2: 2026
A3: Mês | B3: Vendas | C3: NF | D3: % | F3: Mês | G3: Vendas | H3: NF | I3: %
A4: JAN | B4: 5327990 | C4: 3558260 | D4: =C4/B4 -> 0.66784285 | F4: JAN | G4: 4672173 | H4: 3295044 | I4: =H4/G4 -> 0.70524871
A5: FEV | B5: 4380090 | C5: 3088730 | D5: =C5/B5 -> 0.70517501 | F5: FEV | G5: 4188811.9 | H5: 2887442.9 | I5: =H5/G5 -> 0.68932264
A6: MAR | B6: 4176190 | C6: 2779560 | D6: =C6/B6 -> 0.66557317 | F6: MAR | G6: 4426713 | I6: =H6/G6 -> 0
A7: ABR | B7: 4096060 | C7: 2913055 | D7: =C7/B7 -> 0.71118465 | F7: ABR | I7: =H7/G7 -> #DIV/0!
A8: MAI | B8: 3756703 | C8: 2724010 | D8: =C8/B8 -> 0.72510656 | F8: MAI | I8: =H8/G8 -> #DIV/0!
A9: JUN | B9: 3436274 | C9: 2446032 | D9: =C9/B9 -> 0.71182682 | F9: JUN | I9: =H9/G9 -> #DIV/0!
A10: JUL | B10: 4782688 | C10: 3373154 | D10: =C10/B10 -> 0.70528414 | F10: JUL | I10: =H10/G10 -> #DIV/0!
A11: AGO | B11: 4502634 | C11: 2923416 | D11: =C11/B11 -> 0.64926796 | F11: AGO | I11: =H11/G11 -> #DIV/0!
A12: SET | B12: 4020626 | C12: 2810746 | D12: =C12/B12 -> 0.69908169 | F12: SET | I12: =H12/G12 -> #DIV/0!
A13: OUT | B13: 4212964 | C13: 2980945 | D13: =C13/B13 -> 0.70756479 | F13: OUT | I13: =H13/G13 -> #DIV/0!
A14: NOV | B14: 3968543 | C14: 2851289 | D14: =C14/B14 -> 0.7184725 | F14: NOV | I14: =H14/G14 -> #DIV/0!
A15: DEZ | B15: 4095062 | C15: 4388856 | D15: =C15/B15 -> 1.0717435 | F15: DEZ | I15: =H15/G15 -> #DIV/0!
B16: =SUM(B4:B15) -> 50755824 | C16: =SUM(C4:C15) -> 36838053 | D16: =C16/B16 -> 0.72578967 | G16: =SUM(G4:G15) -> 13287698 | H16: =SUM(H4:H15) -> 6182486.9 | I16: =H16/G16 -> 0.46527901
C18: =B16-C16 -> 13917771 | H18: =G16-H16 -> 7105211

Sheet Despesas Totais 2025
A1: Operacional - 2025
A2: Unidade | B2: Faturamento | C2: Despesas totais (com impostos) | D2: LL | E2: %
A3: ABC | B3: 1651610.2 | C3: 1064517.3 | D3: =B3-C3 -> 587092.9 | E3: =D3/B3 -> 0.35546699
A4: Anália Franco | B4: 1614310 | C4: 1043147 | D4: =B4-C4 -> 571163 | E4: =D4/B4 -> 0.35381246
A5: Belo Horizonte | B5: 3909312.8 | C5: 3501232.4 | D5: =B5-C5 -> 408080.4 | E5: =D5/B5 -> 0.10438674
A6: Brasília | B6: 3510184 | C6: 2512300.3 | D6: =B6-C6 -> 997883.7 | E6: =D6/B6 -> 0.28428245
A7: Campinas | B7: 4159463.4 | C7: 2908045.5 | D7: =B7-C7 -> 1251417.9 | E7: =D7/B7 -> 0.30086042
A8: Campo Grande | B8: 1504378 | C8: 1424701.9 | D8: =B8-C8 -> 79676.1 | E8: =D8/B8 -> 0.052962819
A9: Cuiabá | B9: 63000 | C9: 122297.8 | D9: =B9-C9 -> -59297.8 | E9: =D9/B9 -> -0.94123492
A10: Curitiba | B10: 1405479.9 | C10: 1498219.4 | D10: =B10-C10 -> -92739.54 | E10: =D10/B10 -> -0.065984254
A11: Florianópolis | B11: 1236646 | C11: 1266053.3 | D11: =B11-C11 -> -29407.3 | E11: =D11/B11 -> -0.023779885
A12: Fortaleza | B12: 688148 | C12: 972284 | D12: =B12-C12 -> -284136 | E12: =D12/B12 -> -0.41289955
A13: Goiânia | B13: 3010600 | C13: 2226171 | D13: =B13-C13 -> 784429 | E13: =D13/B13 -> 0.2605557
A14: Guarulhos | B14: 1421787 | C14: 848260.6 | D14: =B14-C14 -> 573526.4 | E14: =D14/B14 -> 0.40338419
A15: Itaim Bibi | B15: 3701802 | C15: 2884786 | D15: =B15-C15 -> 817016 | E15: =D15/B15 -> 0.22070764
A16: Joinville | B16: 0 | C16: 4022.87 | D16: =B16-C16 -> -4022.87
A17: Jundiaí | B17: 1303464 | C17: 854991.2 | D17: =B17-C17 -> 448472.8 | E17: =D17/B17 -> 0.34406228
A18: Manaus | B18: 372000 | C18: 664483.1 | D18: =B18-C18 -> -292483.1 | E18: =D18/B18 -> -0.78624489
A19: Piracicaba | B19: 966282 | C19: 727042.6 | D19: =B19-C19 -> 239239.4 | E19: =D19/B19 -> 0.24758756
A20: Porto Alegre | B20: 2305120 | C20: 1824530.1 | D20: =B20-C20 -> 480589.9 | E20: =D20/B20 -> 0.20848802
A21: Recife | B21: 1733942 | C21: 1490620.5 | D21: =B21-C21 -> 243321.5 | E21: =D21/B21 -> 0.14032851
A22: Ribeirão Preto | B22: 5134400 | C22: 3025898.1 | D22: =B22-C22 -> 2108501.9 | E22: =D22/B22 -> 0.41066179
A23: Rio de Janeiro | B23: 1817329 | C23: 2063030.1 | D23: =B23-C23 -> -245701.1 | E23: =D23/B23 -> -0.13519902
A24: Salvador | B24: 1523876 | C24: 1601763.2 | D24: =B24-C24 -> -77887.2 | E24: =D24/B24 -> -0.051111245
A25: Santos | B25: 2038650 | C25: 1601847.4 | D25: =B25-C25 -> 436802.6 | E25: =D25/B25 -> 0.21426071
A26: São José dos Campos | B26: 2110190 | C26: 1506229.6 | D26: =B26-C26 -> 603960.4 | E26: =D26/B26 -> 0.28621138
A27: São Luis | C27: 18979.3 | D27: =B27-C27 -> -18979.3
A28: Sorocaba | B28: 1496950 | C28: 962306 | D28: =B28-C28 -> 534644 | E28: =D28/B28 -> 0.35715555
A29: Uberlândia | B29: 2076900 | C29: 1621743.4 | D29: =B29-C29 -> 455156.6 | E29: =D29/B29 -> 0.21915191
A30: Vitória | C30: 2442 | D30: =B30-C30 -> -2442
A31: Matriz (ref todas unidades) | B31: 0 | C31: 1181515.5 | D31: =B31-C31 -> -1181515.5
A32: TOTAL | B32: =SUM(B3:B31) -> 50755824 | C32: =SUM(C3:C31) -> 41423461 | D32: =B32-C32 -> 9332362.8 | E32: =D32/B32 -> 0.18386782

Sheet Despesas JAN 2026
A3: UNIDADE | B3: RECEITA BRUTA | C3: ISS/PIS/COFINS | D3: DEVOLUÇÕES | E3: RECEITA LIQUIDA | F3: CUSTOS / DESPESAS | G3: EBITDA | H3: MARGEM EBITDA | I3: IRPJ/CSLL | J3: LL | K3: MARGEM LIQUIDA
A4: ABC | B4: 224964 | C4: 8725.46 | D4: 0 | E4: =B4-(C4+D4) -> 216238.54 | F4: 94756.94 | G4: =E4-F4 -> 121481.6 | H4: =G4/E4 -> 0.5617944 | I4: 10228.4 | J4: =G4-I4 -> 111253.2 | K4: =J4/E4 -> 0.51449293
A5: Anália Franco | B5: 135600 | C5: 12565.6 | D5: 0 | E5: =B5-(C5+D5) -> 123034.4 | F5: 66986.66 | G5: =E5-F5 -> 56047.74 | H5: =G5/E5 -> 0.45554528 | I5: 10468.27 | J5: =G5-I5 -> 45579.47 | K5: =J5/E5 -> 0.37046119
A6: Belo Horizonte | B6: 344039 | C6: 19863.28 | D6: 0 | E6: =B6-(C6+D6) -> 324175.72 | F6: 183855.6 | G6: =E6-F6 -> 140320.12 | H6: =G6/E6 -> 0.43285203 | I6: 21948.5 | J6: =G6-I6 -> 118371.62 | K6: =J6/E6 -> 0.36514647
A7: Brasília | B7: 392652 | C7: 18387.4 | D7: 0 | E7: =B7-(C7+D7) -> 374264.6 | F7: 193187.82 | G7: =E7-F7 -> 181076.78 | H7: =G7/E7 -> 0.48382022 | I7: 23257.02 | J7: =G7-I7 -> 157819.76 | K7: =J7/E7 -> 0.42167964
A8: Campinas | B8: 328720 | C8: 23309.48 | D8: 0 | E8: =B8-(C8+D8) -> 305410.52 | F8: 212025.8 | G8: =E8-F8 -> 93384.72 | H8: =G8/E8 -> 0.30576786 | I8: 20049.32 | J8: =G8-I8 -> 73335.4 | K8: =J8/E8 -> 0.24012074
A9: Campo Grande | B9: 161484 | C9: 11926.8 | D9: 0 | E9: =B9-(C9+D9) -> 149557.2 | F9: 114029.09 | G9: =E9-F9 -> 35528.11 | H9: =G9/E9 -> 0.23755533 | I9: 9643.72 | J9: =G9-I9 -> 25884.39 | K9: =J9/E9 -> 0.17307351
A10: Curitiba | B10: 183106 | C10: 16185.01 | D10: 0 | E10: =B10-(C10+D10) -> 166920.99 | F10: 132362.28 | G10: =E10-F10 -> 34558.71 | H10: =G10/E10 -> 0.20703633 | I10: 8674.25 | J10: =G10-I10 -> 25884.46 | K10: =J10/E10 -> 0.15507013
A11: Florianópolis | B11: 30400 | C11: 12552.05 | D11: 0 | E11: =B11-(C11+D11) -> 17847.95 | F11: 51420.57 | G11: =E11-F11 -> -33572.62 | H11: =G11/E11 -> -1.8810351 | I11: 12706.39 | J11: =G11-I11 -> -46279.01 | K11: =J11/E11 -> -2.5929594
A12: Fortaleza | B12: 98428 | C12: 2054.57 | D12: 0 | E12: =B12-(C12+D12) -> 96373.43 | F12: 87921.47 | G12: =E12-F12 -> 8451.96 | H12: =G12/E12 -> 0.087700106 | I12: 2826.33 | J12: =G12-I12 -> 5625.63 | K12: =J12/E12 -> 0.058373247
A13: Goiânia | B13: 291100 | C13: 15065.05 | D13: 0 | E13: =B13-(C13+D13) -> 276034.95 | F13: 175431.98 | G13: =E13-F13 -> 100602.97 | H13: =G13/E13 -> 0.36445736 | I13: 19344.9 | J13: =G13-I13 -> 81258.07 | K13: =J13/E13 -> 0.29437602
A14: Guarulhos | B14: 177750 | C14: 7031.42 | D14: 0 | E14: =B14-(C14+D14) -> 170718.58 | F14: 86562.1 | G14: =E14-F14 -> 84156.48 | H14: =G14/E14 -> 0.49295443 | I14: 11404.5 | J14: =G14-I14 -> 72751.98 | K14: =J14/E14 -> 0.42615151
A15: Itaim Bibi | B15: 309610 | C15: 16904.35 | D15: 0 | E15: =B15-(C15+D15) -> 292705.65 | F15: 237182.52 | G15: =E15-F15 -> 55523.13 | H15: =G15/E15 -> 0.1896893 | I15: 18285.4 | J15: =G15-I15 -> 37237.73 | K15: =J15/E15 -> 0.12721903
... A27: Uberlândia | B27: 222180 | C27: 11023.15 | D27: 0 | E27: =B27-(C27+D27) -> 211156.85 | F27: 136534.3 | G27: =E27-F27 -> 74622.55 | H27: =G27/E27 -> 0.35339867 | I27: 16080.21 | J27: =G27-I27 -> 58542.34 | K27: =J27/E27 -> 0.27724575
A28: TOTAL | B28: =SUM(B4:B27) -> 4672173 | C28: =SUM(C4:C27) -> 289760.47 | D28: =SUM(D4:D27) -> 0 | E28: =B28-(C28+D28) -> 4382412.5 | F28: =SUM(F4:F27) -> 2968162.3 | G28: =E28-F28 -> 1414250.2 | H28: =G28/E28 -> 0.32271042 | I28: =SUM(I4:I27) -> 309683.74 | J28: =G28-I28 -> 1104566.4 | K28: =J28/E28 -> 0.25204529

Sheet Despesas FEV 2026
A3: UNIDADE | B3: RECEITA BRUTA | C3: ISS/PIS/COFINS | D3: DEVOLUÇÕES | E3: RECEITA LIQUIDA | F3: CUSTOS / DESPESAS | G3: EBITDA | H3: MARGEM EBITDA | I3: IRPJ/CSLL | J3: LL | K3: MARGEM LIQUIDA
A4: ABC | B4: 228210 | C4: 11575.256 | D4: 0 | E4: =B4-(C4+D4) -> 216634.74 | F4: 91792.67 | G4: =E4-F4 -> 124842.07 | H4: =G4/E4 -> 0.57627909 | I4: 0 | J4: =G4-I4 -> 124842.07 | K4: =J4/E4 -> 0.57627909
A5: Anália Franco | B5: 209420 | C5: 5429.65 | D5: 0 | E5: =B5-(C5+D5) -> 203990.35 | F5: 87848.5 | G5: =E5-F5 -> 116141.85 | H5: =G5/E5 -> 0.56934973 | I5: 0 | J5: =G5-I5 -> 116141.85 | K5: =J5/E5 -> 0.56934973
A6: Belo Horizonte | B6: 326850 | C6: 17981.6 | D6: 0 | E6: =B6-(C6+D6) -> 308868.4 | F6: 225688.24 | G6: =E6-F6 -> 83180.16 | H6: =G6/E6 -> 0.26930615 | I6: 0 | J6: =G6-I6 -> 83180.16 | K6: =J6/E6 -> 0.26930615
A7: Brasília | B7: 272510 | C7: 21447.4 | D7: 0 | E7: =B7-(C7+D7) -> 251062.6 | F7: 199115.9 | G7: =E7-F7 -> 51946.7 | H7: =G7/E7 -> 0.20690736 | I7: 0 | J7: =G7-I7 -> 51946.7 | K7: =J7/E7 -> 0.20690736
A8: Campinas | B8: 305028 | C8: 16317.924 | D8: 0 | E8: =B8-(C8+D8) -> 288710.08 | F8: 210774.75 | G8: =E8-F8 -> 77935.326 | H8: =G8/E8 -> 0.26994321 | I8: 0 | J8: =G8-I8 -> 77935.326 | K8: =J8/E8 -> 0.26994321
A9: Campo Grande | B9: 119720 | C9: 9134.573 | D9: 0 | E9: =B9-(C9+D9) -> 110585.43 | F9: 103179.22 | G9: =E9-F9 -> 7406.207 | H9: =G9/E9 -> 0.066972721 | I9: 0 | J9: =G9-I9 -> 7406.207 | K9: =J9/E9 -> 0.066972721
A10: Curitiba | B10: 174069.86 | C10: 11113.001 | D10: 0 | E10: =B10-(C10+D10) -> 162956.86 | F10: 132801.57 | G10: =E10-F10 -> 30155.289 | H10: =G10/E10 -> 0.18505075 | I10: 0 | J10: =G10-I10 -> 30155.289 | K10: =J10/E10 -> 0.18505075
A11: Florianópolis | B11: 67610 | C11: 1717.6 | D11: 0 | E11: =B11-(C11+D11) -> 65892.4 | F11: 75055.32 | G11: =E11-F11 -> -9162.92 | H11: =G11/E11 -> -0.13905883 | I11: 0 | J11: =G11-I11 -> -9162.92 | K11: =J11/E11 -> -0.13905883
A12: Fortaleza | B12: 0 | C12: 5724.489 | D12: 0 | E12: =B12-(C12+D12) -> -5724.489 | F12: 54621.21 | G12: =E12-F12 -> -60345.699 | H12: . | I12: 0 | J12: =G12-I12 -> -60345.699 | K12: .
A13: Goiânia | B13: 205000 | C13: 17674.8 | D13: 0 | E13: =B13-(C13+D13) -> 187325.2 | F13: 164806.09 | G13: =E13-F13 -> 22519.11 | H13: =G13/E13 -> 0.12021399 | I13: 0 | J13: =G13-I13 -> 22519.11 | K13: =J13/E13 -> 0.12021399
A14: Guarulhos | B14: 147182 | C14: 7830.375 | D14: 0 | E14: =B14-(C14+D14) -> 139351.62 | F14: 69288.61 | G14: =E14-F14 -> 70063.015 | H14: =G14/E14 -> 0.5027786 | I14: 0 | J14: =G14-I14 -> 70063.015 | K14: =J14/E14 -> 0.5027786
A15: Itaim Bibi | B15: 359760 | C15: 11309.266 | D15: 0 | E15: =B15-(C15+D15) -> 348450.73 | F15: 284879.35 | G15: =E15-F15 -> 63571.384 | H15: =G15/E15 -> 0.18244009 | I15: 0 | J15: =G15-I15 -> 63571.384 | K15: =J15/E15 -> 0.18244009
A16: Jundiaí | B16: 71700 | C16: 2932.35 | D16: 0 | E16: =B16-(C16+D16) -> 68767.65 | F16: 54560.69 | G16: =E16-F16 -> 14206.96 | H16: =G16/E16 -> 0.20659365 | I16: 0 | J16: =G16-I16 -> 14206.96 | K16: =J16/E16 -> 0.20659365
A17: Manaus | B17: 0 | C17: 0 | D17: 0 | E17: =B17-(C17+D17) -> 0 | F17: 5000 | G17: =E17-F17 -> -5000 | H17: =G17/E17 -> #DIV/0! | I17: 0 | J17: =G17-I17 -> -5000 | K17: =J17/E17 -> #DIV/0!
A18: Piracicaba | B18: 92350 | C18: 3671.925 | D18: 0 | E18: =B18-(C18+D18) -> 88678.075 | F18: 53597.55 | G18: =E18-F18 -> 35080.525 | H18: =G18/E18 -> 0.39559412 | I18: 0 | J18: =G18-I18 -> 35080.525 | K18: =J18/E18 -> 0.39559412
A19: Porto Alegre | B19: 167512 | C19: 8178.375 | D19: 0 | E19: =B19-(C19+D19) -> 159333.62 | F19: 134755.6 | G19: =E19-F19 -> 24578.025 | H19: =G19/E19 -> 0.1542551 | I19: 0 | J19: =G19-I19 -> 24578.025 | K19: =J19/E19 -> 0.1542551
A20: Recife | B20: 156622 | C20: 9562.229 | D20: 0 | E20: =B20-(C20+D20) -> 147059.77 | F20: 136144.22 | G20: =E20-F20 -> 10915.551 | H20: =G20/E20 -> 0.074225269 | I20: 0 | J20: =G20-I20 -> 10915.551 | K20: =J20/E20 -> 0.074225269
A21: Ribeirão Preto | B21: 320500 | C21: 16051.65 | D21: 0 | E21: =B21-(C21+D21) -> 304448.35 | F21: 199957.68 | G21: =E21-F21 -> 104490.67 | H21: =G21/E21 -> 0.34321313 | I21: 0 | J21: =G21-I21 -> 104490.67 | K21: =J21/E21 -> 0.34321313
A22: Rio de Janeiro | B22: 161000 | C22: 6011.75 | D22: 0 | E22: =B22-(C22+D22) -> 154988.25 | F22: 128775.85 | G22: =E22-F22 -> 26212.4 | H22: =G22/E22 -> 0.16912508 | I22: 0 | J22: =G22-I22 -> 26212.4 | K22: =J22/E22 -> 0.16912508
A23: Salvador | B23: 146552 | C23: 10875.41 | D23: 0 | E23: =B23-(C23+D23) -> 135676.59 | F23: 141588.51 | G23: =E23-F23 -> -5911.92 | H23: =G23/E23 -> -0.043573619 | I23: 0 | J23: =G23-I23 -> -5911.92 | K23: =J23/E23 -> -0.043573619
A24: Santos | B24: 146200 | C24: 5529.633 | D24: 0 | E24: =B24-(C24+D24) -> 140670.37 | F24: 105807.9 | G24: =E24-F24 -> 34862.467 | H24: =G24/E24 -> 0.24783092 | I24: 0 | J24: =G24-I24 -> 34862.467 | K24: =J24/E24 -> 0.24783092
... A27: Uberlândia | B27: 193800 | C27: 9626.47 | D27: 0 | E27: =B27-(C27+D27) -> 184173.53 | F27: 135775.39 | G27: =E27-F27 -> 48398.14 | H27: =G27/E27 -> 0.26278554 | I27: 0 | J27: =G27-I27 -> 48398.14 | K27: =J27/E27 -> 0.26278554
A28: TOTAL | B28: =SUM(B4:B27) -> 4188811.9 | C28: =SUM(C4:C27) -> 221167.03 | D28: =SUM(D4:D27) -> 0 | E28: =B28-(C28+D28) -> 3967644.8 | F28: =SUM(F4:F27) -> 2983796.2 | G28: =E28-F28 -> 983848.61 | H28: =G28/E28 -> 0.24796791 | I28: =SUM(I4:I27) -> 0 | J28: =G28-I28 -> 983848.61 | K28: =J28/E28 -> 0.24796791

Sheet Despesas MAR 2026
A3: UNIDADE | B3: RECEITA BRUTA | C3: ISS/PIS/COFINS | D3: DEVOLUÇÕES | E3: RECEITA LIQUIDA | F3: CUSTOS / DESPESAS | G3: EBITDA | H3: MARGEM EBITDA | I3: IRPJ/CSLL | J3: LL | K3: MARGEM LIQUIDA
A4: ABC | B4: 126264 | C4: 11281.46 | D4: 0 | E4: =B4-(C4+D4) -> 114982.54 | F4: 71401.123 | G4: =E4-F4 -> 43581.417 | H4: =G4/E4 -> 0.37902639 | I4: 0 | J4: =G4-I4 -> 43581.417 | K4: =J4/E4 -> 0.37902639
A5: Anália Franco | B5: 162166 | C5: 10775.63 | D5: 0 | E5: =B5-(C5+D5) -> 151390.37 | F5: 79078.949 | G5: =E5-F5 -> 72311.421 | H5: =G5/E5 -> 0.47764875 | I5: 0 | J5: =G5-I5 -> 72311.421 | K5: =J5/E5 -> 0.47764875
A6: Belo Horizonte | B6: 414860 | C6: 20618.64 | D6: 0 | E6: =B6-(C6+D6) -> 394241.36 | F6: 235807.97 | G6: =E6-F6 -> 158433.39 | H6: =G6/E6 -> 0.40186901 | I6: 3806.63 | J6: =G6-I6 -> 154626.76 | K6: =J6/E6 -> 0.39221343
A7: Brasília | B7: 298142 | C7: 15816.22 | D7: 0 | E7: =B7-(C7+D7) -> 282325.78 | F7: 139577.55 | G7: =E7-F7 -> 142748.23 | H7: =G7/E7 -> 0.50561527 | I7: 0 | J7: =G7-I7 -> 142748.23 | K7: =J7/E7 -> 0.50561527
A8: Campinas | B8: 232484 | C8: 18162.16 | D8: 0 | E8: =B8-(C8+D8) -> 214321.84 | F8: 175474.1 | G8: =E8-F8 -> 38847.74 | H8: =G8/E8 -> 0.1812589 | I8: 0 | J8: =G8-I8 -> 38847.74 | K8: =J8/E8 -> 0.1812589
A9: Campo Grande | B9: 149070 | C9: 7964.53 | D9: 0 | E9: =B9-(C9+D9) -> 141105.47 | F9: 109394.47 | G9: =E9-F9 -> 31711.004 | H9: =G9/E9 -> 0.22473263 | I9: 0 | J9: =G9-I9 -> 31711.004 | K9: =J9/E9 -> 0.22473263
A10: Curitiba | B10: 182489.72 | C10: 7012.31 | D10: 0 | E10: =B10-(C10+D10) -> 175477.41 | F10: 166263.45 | G10: =E10-F10 -> 9213.957 | H10: =G10/E10 -> 0.052507938 | I10: 0 | J10: =G10-I10 -> 9213.957 | K10: =J10/E10 -> 0.052507938
A11: Florianópolis | B11: 14500 | C11: 2130.62 | D11: 0 | E11: =B11-(C11+D11) -> 12369.38 | F11: 61421.197 | G11: =E11-F11 -> -49051.817 | H11: =G11/E11 -> -3.9655841 | I11: 0 | J11: =G11-I11 -> -49051.817 | K11: =J11/E11 -> -3.9655841
A12: Fortaleza | B12: 0 | C12: 0 | D12: 0 | E12: =B12-(C12+D12) -> 0 | F12: 63188.187 | G12: =E12-F12 -> -63188.187 | H12: . | I12: 0 | J12: =G12-I12 -> -63188.187 | K12: .
A13: Goiânia | B13: 198980 | C13: 9974.25 | D13: 0 | E13: =B13-(C13+D13) -> 189005.75 | F13: 159268.01 | G13: =E13-F13 -> 29737.741 | H13: =G13/E13 -> 0.15733776 | I13: 0 | J13: =G13-I13 -> 29737.741 | K13: =J13/E13 -> 0.15733776
A14: Guarulhos | B14: 122250 | C14: 9757.68 | D14: 0 | E14: =B14-(C14+D14) -> 112492.32 | F14: 64818.979 | G14: =E14-F14 -> 47673.341 | H14: =G14/E14 -> 0.42379196 | I14: 0 | J14: =G14-I14 -> 47673.341 | K14: =J14/E14 -> 0.42379196
A15: Itaim Bibi | B15: 469584 | C15: 13164.29 | D15: 0 | E15: =B15-(C15+D15) -> 456419.71 | F15: 364137.81 | G15: =E15-F15 -> 92281.903 | H15: =G15/E15 -> 0.2021865 | I15: 0 | J15: =G15-I15 -> 92281.903 | K15: =J15/E15 -> 0.2021865
A16: Jundiaí | B16: 143010 | C16: 4709.37 | D16: 0 | E16: =B16-(C16+D16) -> 138300.63 | F16: 77521.464 | G16: =E16-F16 -> 60779.166 | H16: =G16/E16 -> 0.43947136 | I16: 0 | J16: =G16-I16 -> 60779.166 | K16: =J16/E16 -> 0.43947136
A17: Manaus | B17: 0 | C17: 0 | D17: 0 | E17: =B17-(C17+D17) -> 0 | F17: 5000 | G17: =E17-F17 -> -5000 | H17: . | I17: 0 | J17: =G17-I17 -> -5000 | K17: .
A18: Piracicaba | B18: 83700 | C18: 5220.28 | D18: 0 | E18: =B18-(C18+D18) -> 78479.72 | F18: 57265.38 | G18: =E18-F18 -> 21214.34 | H18: =G18/E18 -> 0.2703162 | I18: 0 | J18: =G18-I18 -> 21214.34 | K18: =J18/E18 -> 0.2703162
A19: Porto Alegre | B19: 245410 | C19: 5651.06 | D19: 0 | E19: =B19-(C19+D19) -> 239758.94 | F19: 164894.63 | G19: =E19-F19 -> 74864.314 | H19: =G19/E19 -> 0.31224827 | I19: 0 | J19: =G19-I19 -> 74864.314 | K19: =J19/E19 -> 0.31224827
A20: Recife | B20: 194010 | C20: 6289.42 | D20: 0 | E20: =B20-(C20+D20) -> 187720.58 | F20: 126869.25 | G20: =E20-F20 -> 60851.33 | H20: =G20/E20 -> 0.32415908 | I20: 0 | J20: =G20-I20 -> 60851.33 | K20: =J20/E20 -> 0.32415908
A21: Ribeirão Preto | B21: 426900 | C21: 13546.96 | D21: 0 | E21: =B21-(C21+D21) -> 413353.04 | F21: 211071.57 | G21: =E21-F21 -> 202281.47 | H21: =G21/E21 -> 0.48936733 | I21: 0 | J21: =G21-I21 -> 202281.47 | K21: =J21/E21 -> 0.48936733
A22: Rio de Janeiro | B22: 129400 | C22: 8046.26 | D22: 0 | E22: =B22-(C22+D22) -> 121353.74 | F22: 147836.27 | G22: =E22-F22 -> -26482.526 | H22: =G22/E22 -> -0.21822587 | I22: 0 | J22: =G22-I22 -> -26482.526 | K22: =J22/E22 -> -0.21822587
A23: Salvador | B23: 203950 | C23: 6249.67 | D23: 0 | E23: =B23-(C23+D23) -> 197700.33 | F23: 159250.22 | G23: =E23-F23 -> 38450.114 | H23: =G23/E23 -> 0.19448685 | I23: 0 | J23: =G23-I23 -> 38450.114 | K23: =J23/E23 -> 0.19448685
A24: Santos | B24: 106610 | C24: 8139.18 | D24: 0 | E24: =B24-(C24+D24) -> 98470.82 | F24: 84130.249 | G24: =E24-F24 -> 14340.571 | H24: =G24/E24 -> 0.1456327 | I24: 0 | J24: =G24-I24 -> 14340.571 | K24: =J24/E24 -> 0.1456327
A25: São José dos Campos | B25: 255590 | C25: 4607.24 | D25: 0 | E25: =B25-(C25+D25) -> 250982.76 | F25: 153398.67 | G25: =E25-F25 -> 97584.094 | H25: =G25/E25 -> 0.38880796 | I25: 0 | J25: =G25-I25 -> 97584.094 | K25: =J25/E25 -> 0.38880796
A26: Sorocaba | B26: 171643 | C26: 4245.75 | D26: 0 | E26: =B26-(C26+D26) -> 167397.25 | F26: 85839.414 | G26: =E26-F26 -> 81557.836 | H26: =G26/E26 -> 0.48721133 | I26: 0 | J26: =G26-I26 -> 81557.836 | K26: =J26/E26 -> 0.48721133
A27: Uberlândia | B27: 95700 | C27: 8746.2 | D27: 0 | E27: =B27-(C27+D27) -> 86953.8 | F27: 93967.767 | G27: =E27-F27 -> -7013.967 | H27: =G27/E27 -> -0.080663145 | I27: 0 | J27: =G27-I27 -> -7013.967 | K27: =J27/E27 -> -0.080663145
A28: TOTAL | B28: =SUM(B4:B27) -> 4426712.7 | C28: =SUM(C4:C27) -> 202109.18 | D28: =SUM(D4:D27) -> 0 | E28: =B28-(C28+D28) -> 4224603.5 | F28: =SUM(F4:F27) -> 3056876.7 | G28: =E28-F28 -> 1167726.9 | H28: =G28/E28 -> 0.276411 | I28: =SUM(I4:I27) -> 3806.63 | J28: =G28-I28 -> 1163920.2 | K28: =J28/E28 -> 0.27550994

Sheet Despesas ABR 2026
A3: UNIDADE | B3: RECEITA BRUTA | C3: ISS/PIS/COFINS | D3: DEVOLUÇÕES | E3: RECEITA LIQUIDA | F3: CUSTOS / DESPESAS | G3: EBITDA | H3: MARGEM EBITDA | I3: IRPJ/CSLL | J3: LL | K3: MARGEM LIQUIDA
A4: ABC | D4: 0 | E4: =B4-(C4+D4) -> 0 | G4: =E4-F4 -> 0 | H4: =G4/E4 -> #DIV/0! | I4: 0 | J4: =G4-I4 -> 0 | K4: =J4/E4 -> #DIV/0!
A5: Anália Franco | D5: 0 | E5: =B5-(C5+D5) -> 0 | G5: =E5-F5 -> 0 | H5: =G5/E5 -> #DIV/0! | I5: 0 | J5: =G5-I5 -> 0 | K5: =J5/E5 -> #DIV/0!
A6: Belo Horizonte | D6: 0 | E6: =B6-(C6+D6) -> 0 | G6: =E6-F6 -> 0 | H6: =G6/E6 -> #DIV/0! | I6: 0 | J6: =G6-I6 -> 0 | K6: =J6/E6 -> #DIV/0!
A7: Brasília | D7: 0 | E7: =B7-(C7+D7) -> 0 | G7: =E7-F7 -> 0 | H7: =G7/E7 -> #DIV/0! | I7: 0 | J7: =G7-I7 -> 0 | K7: =J7/E7 -> #DIV/0!
A8: Campinas | D8: 0 | E8: =B8-(C8+D8) -> 0 | G8: =E8-F8 -> 0 | H8: =G8/E8 -> #DIV/0! | I8: 0 | J8: =G8-I8 -> 0 | K8: =J8/E8 -> #DIV/0!
A9: Campo Grande | D9: 0 | E9: =B9-(C9+D9) -> 0 | G9: =E9-F9 -> 0 | H9: =G9/E9 -> #DIV/0! | I9: 0 | J9: =G9-I9 -> 0 | K9: =J9/E9 -> #DIV/0!
A10: Curitiba | D10: 0 | E10: =B10-(C10+D10) -> 0 | G10: =E10-F10 -> 0 | H10: =G10/E10 -> #DIV/0! | I10: 0 | J10: =G10-I10 -> 0 | K10: =J10/E10 -> #DIV/0!
A11: Florianópolis | D11: 0 | E11: =B11-(C11+D11) -> 0 | G11: =E11-F11 -> 0 | H11: =G11/E11 -> #DIV/0! | I11: 0 | J11: =G11-I11 -> 0 | K11: =J11/E11 -> #DIV/0!
A12: Fortaleza | D12: 0 | E12: =B12-(C12+D12) -> 0 | G12: =E12-F12 -> 0 | H12: . | I12: 0 | J12: =G12-I12 -> 0 | K12: .
A13: Goiânia | D13: 0 | E13: =B13-(C13+D13) -> 0 | G13: =E13-F13 -> 0 | H13: =G13/E13 -> #DIV/0! | I13: 0 | J13: =G13-I13 -> 0 | K13: =J13/E13 -> #DIV/0!
A14: Guarulhos | D14: 0 | E14: =B14-(C14+D14) -> 0 | G14: =E14-F14 -> 0 | H14: =G14/E14 -> #DIV/0! | I14: 0 | J14: =G14-I14 -> 0 | K14: =J14/E14 -> #DIV/0!
A15: Itaim Bibi | D15: 0 | E15: =B15-(C15+D15) -> 0 | G15: =E15-F15 -> 0 | H15: =G15/E15 -> #DIV/0! | I15: 0 | J15: =G15-I15 -> 0 | K15: =J15/E15 -> #DIV/0!
A16: Jundiaí | D16: 0 | E16: =B16-(C16+D16) -> 0 | G16: =E16-F16 -> 0 | H16: =G16/E16 -> #DIV/0! | I16: 0 | J16: =G16-I16 -> 0 | K16: =J16/E16 -> #DIV/0!
A17: Manaus | D17: 0 | E17: =B17-(C17+D17) -> 0 | G17: =E17-F17 -> 0 | H17: =G17/E17 -> #DIV/0! | I17: 0 | J17: =G17-I17 -> 0 | K17: =J17/E17 -> #DIV/0!
A18: Piracicaba | D18: 0 | E18: =B18-(C18+D18) -> 0 | G18: =E18-F18 -> 0 | H18: =G18/E18 -> #DIV/0! | I18: 0 | J18: =G18-I18 -> 0 | K18: =J18/E18 -> #DIV/0!
A19: Porto Alegre | D19: 0 | E19: =B19-(C19+D19) -> 0 | G19: =E19-F19 -> 0 | H19: =G19/E19 -> #DIV/0! | I19: 0 | J19: =G19-I19 -> 0 | K19: =J19/E19 -> #DIV/0!
A20: Recife | D20: 0 | E20: =B20-(C20+D20) -> 0 | G20: =E20-F20 -> 0 | H20: =G20/E20 -> #DIV/0! | I20: 0 | J20: =G20-I20 -> 0 | K20: =J20/E20 -> #DIV/0!
A21: Ribeirão Preto | D21: 0 | E21: =B21-(C21+D21) -> 0 | G21: =E21-F21 -> 0 | H21: =G21/E21 -> #DIV/0! | I21: 0 | J21: =G21-I21 -> 0 | K21: =J21/E21 -> #DIV/0!
A22: Rio de Janeiro | D22: 0 | E22: =B22-(C22+D22) -> 0 | G22: =E22-F22 -> 0 | H22: =G22/E22 -> #DIV/0! | I22: 0 | J22: =G22-I22 -> 0 | K22: =J22/E22 -> #DIV/0!
A23: Salvador | D23: 0 | E23: =B23-(C23+D23) -> 0 | G23: =E23-F23 -> 0 | H23: =G23/E23 -> #DIV/0! | I23: 0 | J23: =G23-I23 -> 0 | K23: =J23/E23 -> #DIV/0!
A24: Santos | D24: 0 | E24: =B24-(C24+D24) -> 0 | G24: =E24-F24 -> 0 | H24: =G24/E24 -> #DIV/0! | I24: 0 | J24: =G24-I24 -> 0 | K24: =J24/E24 -> #DIV/0!
... A27: Uberlândia | D27: 0 | E27: =B27-(C27+D27) -> 0 | G27: =E27-F27 -> 0 | H27: =G27/E27 -> #DIV/0! | I27: 0 | J27: =G27-I27 -> 0 | K27: =J27/E27 -> #DIV/0!
A28: TOTAL | B28: =SUM(B4:B27) -> 0 | C28: =SUM(C4:C27) -> 0 | D28: =SUM(D4:D27) -> 0 | E28: =B28-(C28+D28) -> 0 | F28: =SUM(F4:F27) -> 0 | G28: =E28-F28 -> 0 | H28: =G28/E28 -> #DIV/0! | I28: =SUM(I4:I27) -> 0 | J28: =G28-I28 -> 0 | K28: =J28/E28 -> #DIV/0!

Sheet Despesas MAI 2026
A3: UNIDADE | B3: RECEITA BRUTA | C3: ISS/PIS/COFINS | D3: DEVOLUÇÕES | E3: RECEITA LIQUIDA | F3: CUSTOS / DESPESAS | G3: EBITDA | H3: MARGEM EBITDA | I3: IRPJ/CSLL | J3: LL | K3: MARGEM LIQUIDA
A4: ABC | D4: 0 | E4: =B4-(C4+D4) -> 0 | G4: =E4-F4 -> 0 | H4: =G4/E4 -> #DIV/0! | I4: 0 | J4: =G4-I4 -> 0 | K4: =J4/E4 -> #DIV/0!
A5: Anália Franco | D5: 0 | E5: =B5-(C5+D5) -> 0 | G5: =E5-F5 -> 0 | H5: =G5/E5 -> #DIV/0! | I5: 0 | J5: =G5-I5 -> 0 | K5: =J5/E5 -> #DIV/0!
A6: Belo Horizonte | D6: 0 | E6: =B6-(C6+D6) -> 0 | G6: =E6-F6 -> 0 | H6: =G6/E6 -> #DIV/0! | I6: 0 | J6: =G6-I6 -> 0 | K6: =J6/E6 -> #DIV/0!
A7: Brasília | D7: 0 | E7: =B7-(C7+D7) -> 0 | G7: =E7-F7 -> 0 | H7: =G7/E7 -> #DIV/0! | I7: 0 | J7: =G7-I7 -> 0 | K7: =J7/E7 -> #DIV/0!
A8: Campinas | D8: 0 | E8: =B8-(C8+D8) -> 0 | G8: =E8-F8 -> 0 | H8: =G8/E8 -> #DIV/0! | I8: 0 | J8: =G8-I8 -> 0 | K8: =J8/E8 -> #DIV/0!
A9: Campo Grande | D9: 0 | E9: =B9-(C9+D9) -> 0 | G9: =E9-F9 -> 0 | H9: =G9/E9 -> #DIV/0! | I9: 0 | J9: =G9-I9 -> 0 | K9: =J9/E9 -> #DIV/0!
A10: Curitiba | D10: 0 | E10: =B10-(C10+D10) -> 0 | G10: =E10-F10 -> 0 | H10: =G10/E10 -> #DIV/0! | I10: 0 | J10: =G10-I10 -> 0 | K10: =J10/E10 -> #DIV/0!
A11: Florianópolis | D11: 0 | E11: =B11-(C11+D11) -> 0 | G11: =E11-F11 -> 0 | H11: =G11/E11 -> #DIV/0! | I11: 0 | J11: =G11-I11 -> 0 | K11: =J11/E11 -> #DIV/0!
A12: Fortaleza | D12: 0 | E12: =B12-(C12+D12) -> 0 | G12: =E12-F12 -> 0 | H12: . | I12: 0 | J12: =G12-I12 -> 0 | K12: .
A13: Goiânia | D13: 0 | E13: =B13-(C13+D13) -> 0 | G13: =E13-F13 -> 0 | H13: =G13/E13 -> #DIV/0! | I13: 0 | J13: =G13-I13 -> 0 | K13: =J13/E13 -> #DIV/0!
A14: Guarulhos | D14: 0 | E14: =B14-(C14+D14) -> 0 | G14: =E14-F14 -> 0 | H14: =G14/E14 -> #DIV/0! | I14: 0 | J14: =G14-I14 -> 0 | K14: =J14/E14 -> #DIV/0!
A15: Itaim Bibi | D15: 0 | E15: =B15-(C15+D15) -> 0 | G15: =E15-F15 -> 0 | H15: =G15/E15 -> #DIV/0! | I15: 0 | J15: =G15-I15 -> 0 | K15: =J15/E15 -> #DIV/0!
A16: Jundiaí | D16: 0 | E16: =B16-(C16+D16) -> 0 | G16: =E16-F16 -> 0 | H16: =G16/E16 -> #DIV/0! | I16: 0 | J16: =G16-I16 -> 0 | K16: =J16/E16 -> #DIV/0!
A17: Manaus | D17: 0 | E17: =B17-(C17+D17) -> 0 | G17: =E17-F17 -> 0 | H17: =G17/E17 -> #DIV/0! | I17: 0 | J17: =G17-I17 -> 0 | K17: =J17/E17 -> #DIV/0!
A18: Piracicaba | D18: 0 | E18: =B18-(C18+D18) -> 0 | G18: =E18-F18 -> 0 | H18: =G18/E18 -> #DIV/0! | I18: 0 | J18: =G18-I18 -> 0 | K18: =J18/E18 -> #DIV/0!
A19: Porto Alegre | D19: 0 | E19: =B19-(C19+D19) -> 0 | G19: =E19-F19 -> 0 | H19: =G19/E19 -> #DIV/0! | I19: 0 | J19: =G19-I19 -> 0 | K19: =J19/E19 -> #DIV/0!
A20: Recife | D20: 0 | E20: =B20-(C20+D20) -> 0 | G20: =E20-F20 -> 0 | H20: =G20/E20 -> #DIV/0! | I20: 0 | J20: =G20-I20 -> 0 | K20: =J20/E20 -> #DIV/0!
A21: Ribeirão Preto | D21: 0 | E21: =B21-(C21+D21) -> 0 | G21: =E21-F21 -> 0 | H21: =G21/E21 -> #DIV/0! | I21: 0 | J21: =G21-I21 -> 0 | K21: =J21/E21 -> #DIV/0!
A22: Rio de Janeiro | D22: 0 | E22: =B22-(C22+D22) -> 0 | G22: =E22-F22 -> 0 | H22: =G22/E22 -> #DIV/0! | I22: 0 | J22: =G22-I22 -> 0 | K22: =J22/E22 -> #DIV/0!
A23: Salvador | D23: 0 | E23: =B23-(C23+D23) -> 0 | G23: =E23-F23 -> 0 | H23: =G23/E23 -> #DIV/0! | I23: 0 | J23: =G23-I23 -> 0 | K23: =J23/E23 -> #DIV/0!
A24: Santos | D24: 0 | E24: =B24-(C24+D24) -> 0 | G24: =E24-F24 -> 0 | H24: =G24/E24 -> #DIV/0! | I24: 0 | J24: =G24-I24 -> 0 | K24: =J24/E24 -> #DIV/0!
... A27: Uberlândia | D27: 0 | E27: =B27-(C27+D27) -> 0 | G27: =E27-F27 -> 0 | H27: =G27/E27 -> #DIV/0! | I27: 0 | J27: =G27-I27 -> 0 | K27: =J27/E27 -> #DIV/0!
A28: TOTAL | B28: =SUM(B4:B27) -> 0 | C28: =SUM(C4:C27) -> 0 | D28: =SUM(D4:D27) -> 0 | E28: =B28-(C28+D28) -> 0 | F28: =SUM(F4:F27) -> 0 | G28: =E28-F28 -> 0 | H28: =G28/E28 -> #DIV/0! | I28: =SUM(I4:I27) -> 0 | J28: =G28-I28 -> 0 | K28: =J28/E28 -> #DIV/0!

Sheet Despesas JUN 2026
A3: UNIDADE | B3: RECEITA BRUTA | C3: ISS/PIS/COFINS | D3: DEVOLUÇÕES | E3: RECEITA LIQUIDA | F3: CUSTOS / DESPESAS | G3: EBITDA | H3: MARGEM EBITDA | I3: IRPJ/CSLL | J3: LL | K3: MARGEM LIQUIDA
A4: ABC | D4: 0 | E4: =B4-(C4+D4) -> 0 | G4: =E4-F4 -> 0 | H4: =G4/E4 -> #DIV/0! | I4: 0 | J4: =G4-I4 -> 0 | K4: =J4/E4 -> #DIV/0!
A5: Anália Franco | D5: 0 | E5: =B5-(C5+D5) -> 0 | G5: =E5-F5 -> 0 | H5: =G5/E5 -> #DIV/0! | I5: 0 | J5: =G5-I5 -> 0 | K5: =J5/E5 -> #DIV/0!
A6: Belo Horizonte | D6: 0 | E6: =B6-(C6+D6) -> 0 | G6: =E6-F6 -> 0 | H6: =G6/E6 -> #DIV/0! | I6: 0 | J6: =G6-I6 -> 0 | K6: =J6/E6 -> #DIV/0!
A7: Brasília | D7: 0 | E7: =B7-(C7+D7) -> 0 | G7: =E7-F7 -> 0 | H7: =G7/E7 -> #DIV/0! | I7: 0 | J7: =G7-I7 -> 0 | K7: =J7/E7 -> #DIV/0!
A8: Campinas | D8: 0 | E8: =B8-(C8+D8) -> 0 | G8: =E8-F8 -> 0 | H8: =G8/E8 -> #DIV/0! | I8: 0 | J8: =G8-I8 -> 0 | K8: =J8/E8 -> #DIV/0!
A9: Campo Grande | D9: 0 | E9: =B9-(C9+D9) -> 0 | G9: =E9-F9 -> 0 | H9: =G9/E9 -> #DIV/0! | I9: 0 | J9: =G9-I9 -> 0 | K9: =J9/E9 -> #DIV/0!
A10: Curitiba | D10: 0 | E10: =B10-(C10+D10) -> 0 | G10: =E10-F10 -> 0 | H10: =G10/E10 -> #DIV/0! | I10: 0 | J10: =G10-I10 -> 0 | K10: =J10/E10 -> #DIV/0!
A11: Florianópolis | D11: 0 | E11: =B11-(C11+D11) -> 0 | G11: =E11-F11 -> 0 | H11: =G11/E11 -> #DIV/0! | I11: 0 | J11: =G11-I11 -> 0 | K11: =J11/E11 -> #DIV/0!
A12: Fortaleza | D12: 0 | E12: =B12-(C12+D12) -> 0 | G12: =E12-F12 -> 0 | H12: . | I12: 0 | J12: =G12-I12 -> 0 | K12: .
A13: Goiânia | D13: 0 | E13: =B13-(C13+D13) -> 0 | G13: =E13-F13 -> 0 | H13: =G13/E13 -> #DIV/0! | I13: 0 | J13: =G13-I13 -> 0 | K13: =J13/E13 -> #DIV/0!
A14: Guarulhos | D14: 0 | E14: =B14-(C14+D14) -> 0 | G14: =E14-F14 -> 0 | H14: =G14/E14 -> #DIV/0! | I14: 0 | J14: =G14-I14 -> 0 | K14: =J14/E14 -> #DIV/0!
A15: Itaim Bibi | D15: 0 | E15: =B15-(C15+D15) -> 0 | G15: =E15-F15 -> 0 | H15: =G15/E15 -> #DIV/0! | I15: 0 | J15: =G15-I15 -> 0 | K15: =J15/E15 -> #DIV/0!
A16: Jundiaí | D16: 0 | E16: =B16-(C16+D16) -> 0 | G16: =E16-F16 -> 0 | H16: =G16/E16 -> #DIV/0! | I16: 0 | J16: =G16-I16 -> 0 | K16: =J16/E16 -> #DIV/0!
A17: Manaus | D17: 0 | E17: =B17-(C17+D17) -> 0 | G17: =E17-F17 -> 0 | H17: =G17/E17 -> #DIV/0! | I17: 0 | J17: =G17-I17 -> 0 | K17: =J17/E17 -> #DIV/0!
A18: Piracicaba | D18: 0 | E18: =B18-(C18+D18) -> 0 | G18: =E18-F18 -> 0 | H18: =G18/E18 -> #DIV/0! | I18: 0 | J18: =G18-I18 -> 0 | K18: =J18/E18 -> #DIV/0!
A19: Porto Alegre | D19: 0 | E19: =B19-(C19+D19) -> 0 | G19: =E19-F19 -> 0 | H19: =G19/E19 -> #DIV/0! | I19: 0 | J19: =G19-I19 -> 0 | K19: =J19/E19 -> #DIV/0!
A20: Recife | D20: 0 | E20: =B20-(C20+D20) -> 0 | G20: =E20-F20 -> 0 | H20: =G20/E20 -> #DIV/0! | I20: 0 | J20: =G20-I20 -> 0 | K20: =J20/E20 -> #DIV/0!
A21: Ribeirão Preto | D21: 0 | E21: =B21-(C21+D21) -> 0 | G21: =E21-F21 -> 0 | H21: =G21/E21 -> #DIV/0! | I21: 0 | J21: =G21-I21 -> 0 | K21: =J21/E21 -> #DIV/0!
A22: Rio de Janeiro | D22: 0 | E22: =B22-(C22+D22) -> 0 | G22: =E22-F22 -> 0 | H22: =G22/E22 -> #DIV/0! | I22: 0 | J22: =G22-I22 -> 0 | K22: =J22/E22 -> #DIV/0!
A23: Salvador | D23: 0 | E23: =B23-(C23+D23) -> 0 | G23: =E23-F23 -> 0 | H23: =G23/E23 -> #DIV/0! | I23: 0 | J23: =G23-I23 -> 0 | K23: =J23/E23 -> #DIV/0!
A24: Santos | D24: 0 | E24: =B24-(C24+D24) -> 0 | G24: =E24-F24 -> 0 | H24: =G24/E24 -> #DIV/0! | I24: 0 | J24: =G24-I24 -> 0 | K24: =J24/E24 -> #DIV/0!
... A27: Uberlândia | D27: 0 | E27: =B27-(C27+D27) -> 0 | G27: =E27-F27 -> 0 | H27: =G27/E27 -> #DIV/0! | I27: 0 | J27: =G27-I27 -> 0 | K27: =J27/E27 -> #DIV/0!
A28: TOTAL | B28: =SUM(B4:B27) -> 0 | C28: =SUM(C4:C27) -> 0 | D28: =SUM(D4:D27) -> 0 | E28: =B28-(C28+D28) -> 0 | F28: =SUM(F4:F27) -> 0 | G28: =E28-F28 -> 0 | H28: =G28/E28 -> #DIV/0! | I28: =SUM(I4:I27) -> 0 | J28: =G28-I28 -> 0 | K28: =J28/E28 -> #DIV/0!

Sheet Despesas JUL 2026
A3: UNIDADE | B3: RECEITA BRUTA | C3: ISS/PIS/COFINS | D3: DEVOLUÇÕES | E3: RECEITA LIQUIDA | F3: CUSTOS / DESPESAS | G3: EBITDA | H3: MARGEM EBITDA | I3: IRPJ/CSLL | J3: LL | K3: MARGEM LIQUIDA
A4: ABC | D4: 0 | E4: =B4-(C4+D4) -> 0 | G4: =E4-F4 -> 0 | H4: =G4/E4 -> #DIV/0! | I4: 0 | J4: =G4-I4 -> 0 | K4: =J4/E4 -> #DIV/0!
A5: Anália Franco | D5: 0 | E5: =B5-(C5+D5) -> 0 | G5: =E5-F5 -> 0 | H5: =G5/E5 -> #DIV/0! | I5: 0 | J5: =G5-I5 -> 0 | K5: =J5/E5 -> #DIV/0!
A6: Belo Horizonte | D6: 0 | E6: =B6-(C6+D6) -> 0 | G6: =E6-F6 -> 0 | H6: =G6/E6 -> #DIV/0! | I6: 0 | J6: =G6-I6 -> 0 | K6: =J6/E6 -> #DIV/0!
A7: Brasília | D7: 0 | E7: =B7-(C7+D7) -> 0 | G7: =E7-F7 -> 0 | H7: =G7/E7 -> #DIV/0! | I7: 0 | J7: =G7-I7 -> 0 | K7: =J7/E7 -> #DIV/0!
A8: Campinas | D8: 0 | E8: =B8-(C8+D8) -> 0 | G8: =E8-F8 -> 0 | H8: =G8/E8 -> #DIV/0! | I8: 0 | J8: =G8-I8 -> 0 | K8: =J8/E8 -> #DIV/0!
A9: Campo Grande | D9: 0 | E9: =B9-(C9+D9) -> 0 | G9: =E9-F9 -> 0 | H9: =G9/E9 -> #DIV/0! | I9: 0 | J9: =G9-I9 -> 0 | K9: =J9/E9 -> #DIV/0!
A10: Curitiba | D10: 0 | E10: =B10-(C10+D10) -> 0 | G10: =E10-F10 -> 0 | H10: =G10/E10 -> #DIV/0! | I10: 0 | J10: =G10-I10 -> 0 | K10: =J10/E10 -> #DIV/0!
A11: Florianópolis | D11: 0 | E11: =B11-(C11+D11) -> 0 | G11: =E11-F11 -> 0 | H11: =G11/E11 -> #DIV/0! | I11: 0 | J11: =G11-I11 -> 0 | K11: =J11/E11 -> #DIV/0!
A12: Fortaleza | D12: 0 | E12: =B12-(C12+D12) -> 0 | G12: =E12-F12 -> 0 | H12: . | I12: 0 | J12: =G12-I12 -> 0 | K12: .
A13: Goiânia | D13: 0 | E13: =B13-(C13+D13) -> 0 | G13: =E13-F13 -> 0 | H13: =G13/E13 -> #DIV/0! | I13: 0 | J13: =G13-I13 -> 0 | K13: =J13/E13 -> #DIV/0!
A14: Guarulhos | D14: 0 | E14: =B14-(C14+D14) -> 0 | G14: =E14-F14 -> 0 | H14: =G14/E14 -> #DIV/0! | I14: 0 | J14: =G14-I14 -> 0 | K14: =J14/E14 -> #DIV/0!
A15: Itaim Bibi | D15: 0 | E15: =B15-(C15+D15) -> 0 | G15: =E15-F15 -> 0 | H15: =G15/E15 -> #DIV/0! | I15: 0 | J15: =G15-I15 -> 0 | K15: =J15/E15 -> #DIV/0!
A16: Jundiaí | D16: 0 | E16: =B16-(C16+D16) -> 0 | G16: =E16-F16 -> 0 | H16: =G16/E16 -> #DIV/0! | I16: 0 | J16: =G16-I16 -> 0 | K16: =J16/E16 -> #DIV/0!
A17: Manaus | D17: 0 | E17: =B17-(C17+D17) -> 0 | G17: =E17-F17 -> 0 | H17: =G17/E17 -> #DIV/0! | I17: 0 | J17: =G17-I17 -> 0 | K17: =J17/E17 -> #DIV/0!
A18: Piracicaba | D18: 0 | E18: =B18-(C18+D18) -> 0 | G18: =E18-F18 -> 0 | H18: =G18/E18 -> #DIV/0! | I18: 0 | J18: =G18-I18 -> 0 | K18: =J18/E18 -> #DIV/0!
A19: Porto Alegre | D19: 0 | E19: =B19-(C19+D19) -> 0 | G19: =E19-F19 -> 0 | H19: =G19/E19 -> #DIV/0! | I19: 0 | J19: =G19-I19 -> 0 | K19: =J19/E19 -> #DIV/0!
A20: Recife | D20: 0 | E20: =B20-(C20+D20) -> 0 | G20: =E20-F20 -> 0 | H20: =G20/E20 -> #DIV/0! | I20: 0 | J20: =G20-I20 -> 0 | K20: =J20/E20 -> #DIV/0!
A21: Ribeirão Preto | D21: 0 | E21: =B21-(C21+D21) -> 0 | G21: =E21-F21 -> 0 | H21: =G21/E21 -> #DIV/0! | I21: 0 | J21: =G21-I21 -> 0 | K21: =J21/E21 -> #DIV/0!
A22: Rio de Janeiro | D22: 0 | E22: =B22-(C22+D22) -> 0 | G22: =E22-F22 -> 0 | H22: =G22/E22 -> #DIV/0! | I22: 0 | J22: =G22-I22 -> 0 | K22: =J22/E22 -> #DIV/0!
A23: Salvador | D23: 0 | E23: =B23-(C23+D23) -> 0 | G23: =E23-F23 -> 0 | H23: =G23/E23 -> #DIV/0! | I23: 0 | J23: =G23-I23 -> 0 | K23: =J23/E23 -> #DIV/0!
A24: Santos | D24: 0 | E24: =B24-(C24+D24) -> 0 | G24: =E24-F24 -> 0 | H24: =G24/E24 -> #DIV/0! | I24: 0 | J24: =G24-I24 -> 0 | K24: =J24/E24 -> #DIV/0!
... A27: Uberlândia | D27: 0 | E27: =B27-(C27+D27) -> 0 | G27: =E27-F27 -> 0 | H27: =G27/E27 -> #DIV/0! | I27: 0 | J27: =G27-I27 -> 0 | K27: =J27/E27 -> #DIV/0!
A28: TOTAL | B28: =SUM(B4:B27) -> 0 | C28: =SUM(C4:C27) -> 0 | D28: =SUM(D4:D27) -> 0 | E28: =B28-(C28+D28) -> 0 | F28: =SUM(F4:F27) -> 0 | G28: =E28-F28 -> 0 | H28: =G28/E28 -> #DIV/0! | I28: =SUM(I4:I27) -> 0 | J28: =G28-I28 -> 0 | K28: =J28/E28 -> #DIV/0!

Sheet Despesas AGO 2026
A3: UNIDADE | B3: RECEITA BRUTA | C3: ISS/PIS/COFINS | D3: DEVOLUÇÕES | E3: RECEITA LIQUIDA | F3: CUSTOS / DESPESAS | G3: EBITDA | H3: MARGEM EBITDA | I3: IRPJ/CSLL | J3: LL | K3: MARGEM LIQUIDA
A4: ABC | D4: 0 | E4: =B4-(C4+D4) -> 0 | G4: =E4-F4 -> 0 | H4: =G4/E4 -> #DIV/0! | I4: 0 | J4: =G4-I4 -> 0 | K4: =J4/E4 -> #DIV/0!
A5: Anália Franco | D5: 0 | E5: =B5-(C5+D5) -> 0 | G5: =E5-F5 -> 0 | H5: =G5/E5 -> #DIV/0! | I5: 0 | J5: =G5-I5 -> 0 | K5: =J5/E5 -> #DIV/0!
A6: Belo Horizonte | D6: 0 | E6: =B6-(C6+D6) -> 0 | G6: =E6-F6 -> 0 | H6: =G6/E6 -> #DIV/0! | I6: 0 | J6: =G6-I6 -> 0 | K6: =J6/E6 -> #DIV/0!
A7: Brasília | D7: 0 | E7: =B7-(C7+D7) -> 0 | G7: =E7-F7 -> 0 | H7: =G7/E7 -> #DIV/0! | I7: 0 | J7: =G7-I7 -> 0 | K7: =J7/E7 -> #DIV/0!
A8: Campinas | D8: 0 | E8: =B8-(C8+D8) -> 0 | G8: =E8-F8 -> 0 | H8: =G8/E8 -> #DIV/0! | I8: 0 | J8: =G8-I8 -> 0 | K8: =J8/E8 -> #DIV/0!
A9: Campo Grande | D9: 0 | E9: =B9-(C9+D9) -> 0 | G9: =E9-F9 -> 0 | H9: =G9/E9 -> #DIV/0! | I9: 0 | J9: =G9-I9 -> 0 | K9: =J9/E9 -> #DIV/0!
A10: Curitiba | D10: 0 | E10: =B10-(C10+D10) -> 0 | G10: =E10-F10 -> 0 | H10: =G10/E10 -> #DIV/0! | I10: 0 | J10: =G10-I10 -> 0 | K10: =J10/E10 -> #DIV/0!
A11: Florianópolis | D11: 0 | E11: =B11-(C11+D11) -> 0 | G11: =E11-F11 -> 0 | H11: =G11/E11 -> #DIV/0! | I11: 0 | J11: =G11-I11 -> 0 | K11: =J11/E11 -> #DIV/0!
A12: Fortaleza | D12: 0 | E12: =B12-(C12+D12) -> 0 | G12: =E12-F12 -> 0 | H12: . | I12: 0 | J12: =G12-I12 -> 0 | K12: .
A13: Goiânia | D13: 0 | E13: =B13-(C13+D13) -> 0 | G13: =E13-F13 -> 0 | H13: =G13/E13 -> #DIV/0! | I13: 0 | J13: =G13-I13 -> 0 | K13: =J13/E13 -> #DIV/0!
A14: Guarulhos | D14: 0 | E14: =B14-(C14+D14) -> 0 | G14: =E14-F14 -> 0 | H14: =G14/E14 -> #DIV/0! | I14: 0 | J14: =G14-I14 -> 0 | K14: =J14/E14 -> #DIV/0!
A15: Itaim Bibi | D15: 0 | E15: =B15-(C15+D15) -> 0 | G15: =E15-F15 -> 0 | H15: =G15/E15 -> #DIV/0! | I15: 0 | J15: =G15-I15 -> 0 | K15: =J15/E15 -> #DIV/0!
A16: Jundiaí | D16: 0 | E16: =B16-(C16+D16) -> 0 | G16: =E16-F16 -> 0 | H16: =G16/E16 -> #DIV/0! | I16: 0 | J16: =G16-I16 -> 0 | K16: =J16/E16 -> #DIV/0!
A17: Manaus | D17: 0 | E17: =B17-(C17+D17) -> 0 | G17: =E17-F17 -> 0 | H17: =G17/E17 -> #DIV/0! | I17: 0 | J17: =G17-I17 -> 0 | K17: =J17/E17 -> #DIV/0!
A18: Piracicaba | D18: 0 | E18: =B18-(C18+D18) -> 0 | G18: =E18-F18 -> 0 | H18: =G18/E18 -> #DIV/0! | I18: 0 | J18: =G18-I18 -> 0 | K18: =J18/E18 -> #DIV/0!
A19: Porto Alegre | D19: 0 | E19: =B19-(C19+D19) -> 0 | G19: =E19-F19 -> 0 | H19: =G19/E19 -> #DIV/0! | I19: 0 | J19: =G19-I19 -> 0 | K19: =J19/E19 -> #DIV/0!
A20: Recife | D20: 0 | E20: =B20-(C20+D20) -> 0 | G20: =E20-F20 -> 0 | H20: =G20/E20 -> #DIV/0! | I20: 0 | J20: =G20-I20 -> 0 | K20: =J20/E20 -> #DIV/0!
A21: Ribeirão Preto | D21: 0 | E21: =B21-(C21+D21) -> 0 | G21: =E21-F21 -> 0 | H21: =G21/E21 -> #DIV/0! | I21: 0 | J21: =G21-I21 -> 0 | K21: =J21/E21 -> #DIV/0!
A22: Rio de Janeiro | D22: 0 | E22: =B22-(C22+D22) -> 0 | G22: =E22-F22 -> 0 | H22: =G22/E22 -> #DIV/0! | I22: 0 | J22: =G22-I22 -> 0 | K22: =J22/E22 -> #DIV/0!
A23: Salvador | D23: 0 | E23: =B23-(C23+D23) -> 0 | G23: =E23-F23 -> 0 | H23: =G23/E23 -> #DIV/0! | I23: 0 | J23: =G23-I23 -> 0 | K23: =J23/E23 -> #DIV/0!
A24: Santos | D24: 0 | E24: =B24-(C24+D24) -> 0 | G24: =E24-F24 -> 0 | H24: =G24/E24 -> #DIV/0! | I24: 0 | J24: =G24-I24 -> 0 | K24: =J24/E24 -> #DIV/0!
... A27: Uberlândia | D27: 0 | E27: =B27-(C27+D27) -> 0 | G27: =E27-F27 -> 0 | H27: =G27/E27 -> #DIV/0! | I27: 0 | J27: =G27-I27 -> 0 | K27: =J27/E27 -> #DIV/0!
A28: TOTAL | B28: =SUM(B4:B27) -> 0 | C28: =SUM(C4:C27) -> 0 | D28: =SUM(D4:D27) -> 0 | E28: =B28-(C28+D28) -> 0 | F28: =SUM(F4:F27) -> 0 | G28: =E28-F28 -> 0 | H28: =G28/E28 -> #DIV/0! | I28: =SUM(I4:I27) -> 0 | J28: =G28-I28 -> 0 | K28: =J28/E28 -> #DIV/0!

Sheet Despesas SET 2026
A3: UNIDADE | B3: RECEITA BRUTA | C3: ISS/PIS/COFINS | D3: DEVOLUÇÕES | E3: RECEITA LIQUIDA | F3: CUSTOS / DESPESAS | G3: EBITDA | H3: MARGEM EBITDA | I3: IRPJ/CSLL | J3: LL | K3: MARGEM LIQUIDA
A4: ABC | D4: 0 | E4: =B4-(C4+D4) -> 0 | G4: =E4-F4 -> 0 | H4: =G4/E4 -> #DIV/0! | I4: 0 | J4: =G4-I4 -> 0 | K4: =J4/E4 -> #DIV/0!
A5: Anália Franco | D5: 0 | E5: =B5-(C5+D5) -> 0 | G5: =E5-F5 -> 0 | H5: =G5/E5 -> #DIV/0! | I5: 0 | J5: =G5-I5 -> 0 | K5: =J5/E5 -> #DIV/0!
A6: Belo Horizonte | D6: 0 | E6: =B6-(C6+D6) -> 0 | G6: =E6-F6 -> 0 | H6: =G6/E6 -> #DIV/0! | I6: 0 | J6: =G6-I6 -> 0 | K6: =J6/E6 -> #DIV/0!
A7: Brasília | D7: 0 | E7: =B7-(C7+D7) -> 0 | G7: =E7-F7 -> 0 | H7: =G7/E7 -> #DIV/0! | I7: 0 | J7: =G7-I7 -> 0 | K7: =J7/E7 -> #DIV/0!
A8: Campinas | D8: 0 | E8: =B8-(C8+D8) -> 0 | G8: =E8-F8 -> 0 | H8: =G8/E8 -> #DIV/0! | I8: 0 | J8: =G8-I8 -> 0 | K8: =J8/E8 -> #DIV/0!
A9: Campo Grande | D9: 0 | E9: =B9-(C9+D9) -> 0 | G9: =E9-F9 -> 0 | H9: =G9/E9 -> #DIV/0! | I9: 0 | J9: =G9-I9 -> 0 | K9: =J9/E9 -> #DIV/0!
A10: Curitiba | D10: 0 | E10: =B10-(C10+D10) -> 0 | G10: =E10-F10 -> 0 | H10: =G10/E10 -> #DIV/0! | I10: 0 | J10: =G10-I10 -> 0 | K10: =J10/E10 -> #DIV/0!
A11: Florianópolis | D11: 0 | E11: =B11-(C11+D11) -> 0 | G11: =E11-F11 -> 0 | H11: =G11/E11 -> #DIV/0! | I11: 0 | J11: =G11-I11 -> 0 | K11: =J11/E11 -> #DIV/0!
A12: Fortaleza | D12: 0 | E12: =B12-(C12+D12) -> 0 | G12: =E12-F12 -> 0 | H12: . | I12: 0 | J12: =G12-I12 -> 0 | K12: .
A13: Goiânia | D13: 0 | E13: =B13-(C13+D13) -> 0 | G13: =E13-F13 -> 0 | H13: =G13/E13 -> #DIV/0! | I13: 0 | J13: =G13-I13 -> 0 | K13: =J13/E13 -> #DIV/0!
A14: Guarulhos | D14: 0 | E14: =B14-(C14+D14) -> 0 | G14: =E14-F14 -> 0 | H14: =G14/E14 -> #DIV/0! | I14: 0 | J14: =G14-I14 -> 0 | K14: =J14/E14 -> #DIV/0!
A15: Itaim Bibi | D15: 0 | E15: =B15-(C15+D15) -> 0 | G15: =E15-F15 -> 0 | H15: =G15/E15 -> #DIV/0! | I15: 0 | J15: =G15-I15 -> 0 | K15: =J15/E15 -> #DIV/0!
A16: Jundiaí | D16: 0 | E16: =B16-(C16+D16) -> 0 | G16: =E16-F16 -> 0 | H16: =G16/E16 -> #DIV/0! | I16: 0 | J16: =G16-I16 -> 0 | K16: =J16/E16 -> #DIV/0!
A17: Manaus | D17: 0 | E17: =B17-(C17+D17) -> 0 | G17: =E17-F17 -> 0 | H17: =G17/E17 -> #DIV/0! | I17: 0 | J17: =G17-I17 -> 0 | K17: =J17/E17 -> #DIV/0!
A18: Piracicaba | D18: 0 | E18: =B18-(C18+D18) -> 0 | G18: =E18-F18 -> 0 | H18: =G18/E18 -> #DIV/0! | I18: 0 | J18: =G18-I18 -> 0 | K18: =J18/E18 -> #DIV/0!
A19: Porto Alegre | D19: 0 | E19: =B19-(C19+D19) -> 0 | G19: =E19-F19 -> 0 | H19: =G19/E19 -> #DIV/0! | I19: 0 | J19: =G19-I19 -> 0 | K19: =J19/E19 -> #DIV/0!
A20: Recife | D20: 0 | E20: =B20-(C20+D20) -> 0 | G20: =E20-F20 -> 0 | H20: =G20/E20 -> #DIV/0! | I20: 0 | J20: =G20-I20 -> 0 | K20: =J20/E20 -> #DIV/0!
A21: Ribeirão Preto | D21: 0 | E21: =B21-(C21+D21) -> 0 | G21: =E21-F21 -> 0 | H21: =G21/E21 -> #DIV/0! | I21: 0 | J21: =G21-I21 -> 0 | K21: =J21/E21 -> #DIV/0!
A22: Rio de Janeiro | D22: 0 | E22: =B22-(C22+D22) -> 0 | G22: =E22-F22 -> 0 | H22: =G22/E22 -> #DIV/0! | I22: 0 | J22: =G22-I22 -> 0 | K22: =J22/E22 -> #DIV/0!
A23: Salvador | D23: 0 | E23: =B23-(C23+D23) -> 0 | G23: =E23-F23 -> 0 | H23: =G23/E23 -> #DIV/0! | I23: 0 | J23: =G23-I23 -> 0 | K23: =J23/E23 -> #DIV/0!
A24: Santos | D24: 0 | E24: =B24-(C24+D24) -> 0 | G24: =E24-F24 -> 0 | H24: =G24/E24 -> #DIV/0! | I24: 0 | J24: =G24-I24 -> 0 | K24: =J24/E24 -> #DIV/0!
... A27: Uberlândia | D27: 0 | E27: =B27-(C27+D27) -> 0 | G27: =E27-F27 -> 0 | H27: =G27/E27 -> #DIV/0! | I27: 0 | J27: =G27-I27 -> 0 | K27: =J27/E27 -> #DIV/0!
A28: TOTAL | B28: =SUM(B4:B27) -> 0 | C28: =SUM(C4:C27) -> 0 | D28: =SUM(D4:D27) -> 0 | E28: =B28-(C28+D28) -> 0 | F28: =SUM(F4:F27) -> 0 | G28: =E28-F28 -> 0 | H28: =G28/E28 -> #DIV/0! | I28: =SUM(I4:I27) -> 0 | J28: =G28-I28 -> 0 | K28: =J28/E28 -> #DIV/0!

Sheet Despesas OUT 2026
A3: UNIDADE | B3: RECEITA BRUTA | C3: ISS/PIS/COFINS | D3: DEVOLUÇÕES | E3: RECEITA LIQUIDA | F3: CUSTOS / DESPESAS | G3: EBITDA | H3: MARGEM EBITDA | I3: IRPJ/CSLL | J3: LL | K3: MARGEM LIQUIDA
A4: ABC | D4: 0 | E4: =B4-(C4+D4) -> 0 | G4: =E4-F4 -> 0 | H4: =G4/E4 -> #DIV/0! | I4: 0 | J4: =G4-I4 -> 0 | K4: =J4/E4 -> #DIV/0!
A5: Anália Franco | D5: 0 | E5: =B5-(C5+D5) -> 0 | G5: =E5-F5 -> 0 | H5: =G5/E5 -> #DIV/0! | I5: 0 | J5: =G5-I5 -> 0 | K5: =J5/E5 -> #DIV/0!
A6: Belo Horizonte | D6: 0 | E6: =B6-(C6+D6) -> 0 | G6: =E6-F6 -> 0 | H6: =G6/E6 -> #DIV/0! | I6: 0 | J6: =G6-I6 -> 0 | K6: =J6/E6 -> #DIV/0!
A7: Brasília | D7: 0 | E7: =B7-(C7+D7) -> 0 | G7: =E7-F7 -> 0 | H7: =G7/E7 -> #DIV/0! | I7: 0 | J7: =G7-I7 -> 0 | K7: =J7/E7 -> #DIV/0!
A8: Campinas | D8: 0 | E8: =B8-(C8+D8) -> 0 | G8: =E8-F8 -> 0 | H8: =G8/E8 -> #DIV/0! | I8: 0 | J8: =G8-I8 -> 0 | K8: =J8/E8 -> #DIV/0!
A9: Campo Grande | D9: 0 | E9: =B9-(C9+D9) -> 0 | G9: =E9-F9 -> 0 | H9: =G9/E9 -> #DIV/0! | I9: 0 | J9: =G9-I9 -> 0 | K9: =J9/E9 -> #DIV/0!
A10: Curitiba | D10: 0 | E10: =B10-(C10+D10) -> 0 | G10: =E10-F10 -> 0 | H10: =G10/E10 -> #DIV/0! | I10: 0 | J10: =G10-I10 -> 0 | K10: =J10/E10 -> #DIV/0!
A11: Florianópolis | D11: 0 | E11: =B11-(C11+D11) -> 0 | G11: =E11-F11 -> 0 | H11: =G11/E11 -> #DIV/0! | I11: 0 | J11: =G11-I11 -> 0 | K11: =J11/E11 -> #DIV/0!
A12: Fortaleza | D12: 0 | E12: =B12-(C12+D12) -> 0 | G12: =E12-F12 -> 0 | H12: . | I12: 0 | J12: =G12-I12 -> 0 | K12: .
A13: Goiânia | D13: 0 | E13: =B13-(C13+D13) -> 0 | G13: =E13-F13 -> 0 | H13: =G13/E13 -> #DIV/0! | I13: 0 | J13: =G13-I13 -> 0 | K13: =J13/E13 -> #DIV/0!
A14: Guarulhos | D14: 0 | E14: =B14-(C14+D14) -> 0 | G14: =E14-F14 -> 0 | H14: =G14/E14 -> #DIV/0! | I14: 0 | J14: =G14-I14 -> 0 | K14: =J14/E14 -> #DIV/0!
A15: Itaim Bibi | D15: 0 | E15: =B15-(C15+D15) -> 0 | G15: =E15-F15 -> 0 | H15: =G15/E15 -> #DIV/0! | I15: 0 | J15: =G15-I15 -> 0 | K15: =J15/E15 -> #DIV/0!
A16: Jundiaí | D16: 0 | E16: =B16-(C16+D16) -> 0 | G16: =E16-F16 -> 0 | H16: =G16/E16 -> #DIV/0! | I16: 0 | J16: =G16-I16 -> 0 | K16: =J16/E16 -> #DIV/0!
A17: Manaus | D17: 0 | E17: =B17-(C17+D17) -> 0 | G17: =E17-F17 -> 0 | H17: =G17/E17 -> #DIV/0! | I17: 0 | J17: =G17-I17 -> 0 | K17: =J17/E17 -> #DIV/0!
A18: Piracicaba | D18: 0 | E18: =B18-(C18+D18) -> 0 | G18: =E18-F18 -> 0 | H18: =G18/E18 -> #DIV/0! | I18: 0 | J18: =G18-I18 -> 0 | K18: =J18/E18 -> #DIV/0!
A19: Porto Alegre | D19: 0 | E19: =B19-(C19+D19) -> 0 | G19: =E19-F19 -> 0 | H19: =G19/E19 -> #DIV/0! | I19: 0 | J19: =G19-I19 -> 0 | K19: =J19/E19 -> #DIV/0!
A20: Recife | D20: 0 | E20: =B20-(C20+D20) -> 0 | G20: =E20-F20 -> 0 | H20: =G20/E20 -> #DIV/0! | I20: 0 | J20: =G20-I20 -> 0 | K20: =J20/E20 -> #DIV/0!
A21: Ribeirão Preto | D21: 0 | E21: =B21-(C21+D21) -> 0 | G21: =E21-F21 -> 0 | H21: =G21/E21 -> #DIV/0! | I21: 0 | J21: =G21-I21 -> 0 | K21: =J21/E21 -> #DIV/0!
A22: Rio de Janeiro | D22: 0 | E22: =B22-(C22+D22) -> 0 | G22: =E22-F22 -> 0 | H22: =G22/E22 -> #DIV/0! | I22: 0 | J22: =G22-I22 -> 0 | K22: =J22/E22 -> #DIV/0!
A23: Salvador | D23: 0 | E23: =B23-(C23+D23) -> 0 | G23: =E23-F23 -> 0 | H23: =G23/E23 -> #DIV/0! | I23: 0 | J23: =G23-I23 -> 0 | K23: =J23/E23 -> #DIV/0!
A24: Santos | D24: 0 | E24: =B24-(C24+D24) -> 0 | G24: =E24-F24 -> 0 | H24: =G24/E24 -> #DIV/0! | I24: 0 | J24: =G24-I24 -> 0 | K24: =J24/E24 -> #DIV/0!
... A27: Uberlândia | D27: 0 | E27: =B27-(C27+D27) -> 0 | G27: =E27-F27 -> 0 | H27: =G27/E27 -> #DIV/0! | I27: 0 | J27: =G27-I27 -> 0 | K27: =J27/E27 -> #DIV/0!
A28: TOTAL | B28: =SUM(B4:B27) -> 0 | C28: =SUM(C4:C27) -> 0 | D28: =SUM(D4:D27) -> 0 | E28: =B28-(C28+D28) -> 0 | F28: =SUM(F4:F27) -> 0 | G28: =E28-F28 -> 0 | H28: =G28/E28 -> #DIV/0! | I28: =SUM(I4:I27) -> 0 | J28: =G28-I28 -> 0 | K28: =J28/E28 -> #DIV/0!

Sheet Despesas NOV 2026
A3: UNIDADE | B3: RECEITA BRUTA | C3: ISS/PIS/COFINS | D3: DEVOLUÇÕES | E3: RECEITA LIQUIDA | F3: CUSTOS / DESPESAS | G3: EBITDA | H3: MARGEM EBITDA | I3: IRPJ/CSLL | J3: LL | K3: MARGEM LIQUIDA
A4: ABC | D4: 0 | E4: =B4-(C4+D4) -> 0 | G4: =E4-F4 -> 0 | H4: =G4/E4 -> #DIV/0! | I4: 0 | J4: =G4-I4 -> 0 | K4: =J4/E4 -> #DIV/0!
A5: Anália Franco | D5: 0 | E5: =B5-(C5+D5) -> 0 | G5: =E5-F5 -> 0 | H5: =G5/E5 -> #DIV/0! | I5: 0 | J5: =G5-I5 -> 0 | K5: =J5/E5 -> #DIV/0!
A6: Belo Horizonte | D6: 0 | E6: =B6-(C6+D6) -> 0 | G6: =E6-F6 -> 0 | H6: =G6/E6 -> #DIV/0! | I6: 0 | J6: =G6-I6 -> 0 | K6: =J6/E6 -> #DIV/0!
A7: Brasília | D7: 0 | E7: =B7-(C7+D7) -> 0 | G7: =E7-F7 -> 0 | H7: =G7/E7 -> #DIV/0! | I7: 0 | J7: =G7-I7 -> 0 | K7: =J7/E7 -> #DIV/0!
A8: Campinas | D8: 0 | E8: =B8-(C8+D8) -> 0 | G8: =E8-F8 -> 0 | H8: =G8/E8 -> #DIV/0! | I8: 0 | J8: =G8-I8 -> 0 | K8: =J8/E8 -> #DIV/0!
A9: Campo Grande | D9: 0 | E9: =B9-(C9+D9) -> 0 | G9: =E9-F9 -> 0 | H9: =G9/E9 -> #DIV/0! | I9: 0 | J9: =G9-I9 -> 0 | K9: =J9/E9 -> #DIV/0!
A10: Curitiba | D10: 0 | E10: =B10-(C10+D10) -> 0 | G10: =E10-F10 -> 0 | H10: =G10/E10 -> #DIV/0! | I10: 0 | J10: =G10-I10 -> 0 | K10: =J10/E10 -> #DIV/0!
A11: Florianópolis | D11: 0 | E11: =B11-(C11+D11) -> 0 | G11: =E11-F11 -> 0 | H11: =G11/E11 -> #DIV/0! | I11: 0 | J11: =G11-I11 -> 0 | K11: =J11/E11 -> #DIV/0!
A12: Fortaleza | D12: 0 | E12: =B12-(C12+D12) -> 0 | G12: =E12-F12 -> 0 | H12: . | I12: 0 | J12: =G12-I12 -> 0 | K12: .
A13: Goiânia | D13: 0 | E13: =B13-(C13+D13) -> 0 | G13: =E13-F13 -> 0 | H13: =G13/E13 -> #DIV/0! | I13: 0 | J13: =G13-I13 -> 0 | K13: =J13/E13 -> #DIV/0!
A14: Guarulhos | D14: 0 | E14: =B14-(C14+D14) -> 0 | G14: =E14-F14 -> 0 | H14: =G14/E14 -> #DIV/0! | I14: 0 | J14: =G14-I14 -> 0 | K14: =J14/E14 -> #DIV/0!
A15: Itaim Bibi | D15: 0 | E15: =B15-(C15+D15) -> 0 | G15: =E15-F15 -> 0 | H15: =G15/E15 -> #DIV/0! | I15: 0 | J15: =G15-I15 -> 0 | K15: =J15/E15 -> #DIV/0!
A16: Jundiaí | D16: 0 | E16: =B16-(C16+D16) -> 0 | G16: =E16-F16 -> 0 | H16: =G16/E16 -> #DIV/0! | I16: 0 | J16: =G16-I16 -> 0 | K16: =J16/E16 -> #DIV/0!
A17: Manaus | D17: 0 | E17: =B17-(C17+D17) -> 0 | G17: =E17-F17 -> 0 | H17: =G17/E17 -> #DIV/0! | I17: 0 | J17: =G17-I17 -> 0 | K17: =J17/E17 -> #DIV/0!
A18: Piracicaba | D18: 0 | E18: =B18-(C18+D18) -> 0 | G18: =E18-F18 -> 0 | H18: =G18/E18 -> #DIV/0! | I18: 0 | J18: =G18-I18 -> 0 | K18: =J18/E18 -> #DIV/0!
A19: Porto Alegre | D19: 0 | E19: =B19-(C19+D19) -> 0 | G19: =E19-F19 -> 0 | H19: =G19/E19 -> #DIV/0! | I19: 0 | J19: =G19-I19 -> 0 | K19: =J19/E19 -> #DIV/0!
A20: Recife | D20: 0 | E20: =B20-(C20+D20) -> 0 | G20: =E20-F20 -> 0 | H20: =G20/E20 -> #DIV/0! | I20: 0 | J20: =G20-I20 -> 0 | K20: =J20/E20 -> #DIV/0!
A21: Ribeirão Preto | D21: 0 | E21: =B21-(C21+D21) -> 0 | G21: =E21-F21 -> 0 | H21: =G21/E21 -> #DIV/0! | I21: 0 | J21: =G21-I21 -> 0 | K21: =J21/E21 -> #DIV/0!
A22: Rio de Janeiro | D22: 0 | E22: =B22-(C22+D22) -> 0 | G22: =E22-F22 -> 0 | H22: =G22/E22 -> #DIV/0! | I22: 0 | J22: =G22-I22 -> 0 | K22: =J22/E22 -> #DIV/0!
A23: Salvador | D23: 0 | E23: =B23-(C23+D23) -> 0 | G23: =E23-F23 -> 0 | H23: =G23/E23 -> #DIV/0! | I23: 0 | J23: =G23-I23 -> 0 | K23: =J23/E23 -> #DIV/0!
A24: Santos | D24: 0 | E24: =B24-(C24+D24) -> 0 | G24: =E24-F24 -> 0 | H24: =G24/E24 -> #DIV/0! | I24: 0 | J24: =G24-I24 -> 0 | K24: =J24/E24 -> #DIV/0!
... A27: Uberlândia | D27: 0 | E27: =B27-(C27+D27) -> 0 | G27: =E27-F27 -> 0 | H27: =G27/E27 -> #DIV/0! | I27: 0 | J27: =G27-I27 -> 0 | K27: =J27/E27 -> #DIV/0!
A28: TOTAL | B28: =SUM(B4:B27) -> 0 | C28: =SUM(C4:C27) -> 0 | D28: =SUM(D4:D27) -> 0 | E28: =B28-(C28+D28) -> 0 | F28: =SUM(F4:F27) -> 0 | G28: =E28-F28 -> 0 | H28: =G28/E28 -> #DIV/0! | I28: =SUM(I4:I27) -> 0 | J28: =G28-I28 -> 0 | K28: =J28/E28 -> #DIV/0!

Sheet Despesas DEZ 2026
A3: UNIDADE | B3: RECEITA BRUTA | C3: ISS/PIS/COFINS | D3: DEVOLUÇÕES | E3: RECEITA LIQUIDA | F3: CUSTOS / DESPESAS | G3: EBITDA | H3: MARGEM EBITDA | I3: IRPJ/CSLL | J3: LL | K3: MARGEM LIQUIDA
A4: ABC | D4: 0 | E4: =B4-(C4+D4) -> 0 | G4: =E4-F4 -> 0 | H4: =G4/E4 -> #DIV/0! | I4: 0 | J4: =G4-I4 -> 0 | K4: =J4/E4 -> #DIV/0!
A5: Anália Franco | D5: 0 | E5: =B5-(C5+D5) -> 0 | G5: =E5-F5 -> 0 | H5: =G5/E5 -> #DIV/0! | I5: 0 | J5: =G5-I5 -> 0 | K5: =J5/E5 -> #DIV/0!
A6: Belo Horizonte | D6: 0 | E6: =B6-(C6+D6) -> 0 | G6: =E6-F6 -> 0 | H6: =G6/E6 -> #DIV/0! | I6: 0 | J6: =G6-I6 -> 0 | K6: =J6/E6 -> #DIV/0!
A7: Brasília | D7: 0 | E7: =B7-(C7+D7) -> 0 | G7: =E7-F7 -> 0 | H7: =G7/E7 -> #DIV/0! | I7: 0 | J7: =G7-I7 -> 0 | K7: =J7/E7 -> #DIV/0!
A8: Campinas | D8: 0 | E8: =B8-(C8+D8) -> 0 | G8: =E8-F8 -> 0 | H8: =G8/E8 -> #DIV/0! | I8: 0 | J8: =G8-I8 -> 0 | K8: =J8/E8 -> #DIV/0!
A9: Campo Grande | D9: 0 | E9: =B9-(C9+D9) -> 0 | G9: =E9-F9 -> 0 | H9: =G9/E9 -> #DIV/0! | I9: 0 | J9: =G9-I9 -> 0 | K9: =J9/E9 -> #DIV/0!
A10: Curitiba | D10: 0 | E10: =B10-(C10+D10) -> 0 | G10: =E10-F10 -> 0 | H10: =G10/E10 -> #DIV/0! | I10: 0 | J10: =G10-I10 -> 0 | K10: =J10/E10 -> #DIV/0!
A11: Florianópolis | D11: 0 | E11: =B11-(C11+D11) -> 0 | G11: =E11-F11 -> 0 | H11: =G11/E11 -> #DIV/0! | I11: 0 | J11: =G11-I11 -> 0 | K11: =J11/E11 -> #DIV/0!
A12: Fortaleza | D12: 0 | E12: =B12-(C12+D12) -> 0 | G12: =E12-F12 -> 0 | H12: . | I12: 0 | J12: =G12-I12 -> 0 | K12: .
A13: Goiânia | D13: 0 | E13: =B13-(C13+D13) -> 0 | G13: =E13-F13 -> 0 | H13: =G13/E13 -> #DIV/0! | I13: 0 | J13: =G13-I13 -> 0 | K13: =J13/E13 -> #DIV/0!
A14: Guarulhos | D14: 0 | E14: =B14-(C14+D14) -> 0 | G14: =E14-F14 -> 0 | H14: =G14/E14 -> #DIV/0! | I14: 0 | J14: =G14-I14 -> 0 | K14: =J14/E14 -> #DIV/0!
A15: Itaim Bibi | D15: 0 | E15: =B15-(C15+D15) -> 0 | G15: =E15-F15 -> 0 | H15: =G15/E15 -> #DIV/0! | I15: 0 | J15: =G15-I15 -> 0 | K15: =J15/E15 -> #DIV/0!
A16: Jundiaí | D16: 0 | E16: =B16-(C16+D16) -> 0 | G16: =E16-F16 -> 0 | H16: =G16/E16 -> #DIV/0! | I16: 0 | J16: =G16-I16 -> 0 | K16: =J16/E16 -> #DIV/0!
A17: Manaus | D17: 0 | E17: =B17-(C17+D17) -> 0 | G17: =E17-F17 -> 0 | H17: =G17/E17 -> #DIV/0! | I17: 0 | J17: =G17-I17 -> 0 | K17: =J17/E17 -> #DIV/0!
A18: Piracicaba | D18: 0 | E18: =B18-(C18+D18) -> 0 | G18: =E18-F18 -> 0 | H18: =G18/E18 -> #DIV/0! | I18: 0 | J18: =G18-I18 -> 0 | K18: =J18/E18 -> #DIV/0!
A19: Porto Alegre | D19: 0 | E19: =B19-(C19+D19) -> 0 | G19: =E19-F19 -> 0 | H19: =G19/E19 -> #DIV/0! | I19: 0 | J19: =G19-I19 -> 0 | K19: =J19/E19 -> #DIV/0!
A20: Recife | D20: 0 | E20: =B20-(C20+D20) -> 0 | G20: =E20-F20 -> 0 | H20: =G20/E20 -> #DIV/0! | I20: 0 | J20: =G20-I20 -> 0 | K20: =J20/E20 -> #DIV/0!
A21: Ribeirão Preto | D21: 0 | E21: =B21-(C21+D21) -> 0 | G21: =E21-F21 -> 0 | H21: =G21/E21 -> #DIV/0! | I21: 0 | J21: =G21-I21 -> 0 | K21: =J21/E21 -> #DIV/0!
A22: Rio de Janeiro | D22: 0 | E22: =B22-(C22+D22) -> 0 | G22: =E22-F22 -> 0 | H22: =G22/E22 -> #DIV/0! | I22: 0 | J22: =G22-I22 -> 0 | K22: =J22/E22 -> #DIV/0!
A23: Salvador | D23: 0 | E23: =B23-(C23+D23) -> 0 | G23: =E23-F23 -> 0 | H23: =G23/E23 -> #DIV/0! | I23: 0 | J23: =G23-I23 -> 0 | K23: =J23/E23 -> #DIV/0!
A24: Santos | D24: 0 | E24: =B24-(C24+D24) -> 0 | G24: =E24-F24 -> 0 | H24: =G24/E24 -> #DIV/0! | I24: 0 | J24: =G24-I24 -> 0 | K24: =J24/E24 -> #DIV/0!
... A27: Uberlândia | D27: 0 | E27: =B27-(C27+D27) -> 0 | G27: =E27-F27 -> 0 | H27: =G27/E27 -> #DIV/0! | I27: 0 | J27: =G27-I27 -> 0 | K27: =J27/E27 -> #DIV/0!
A28: TOTAL | B28: =SUM(B4:B27) -> 0 | C28: =SUM(C4:C27) -> 0 | D28: =SUM(D4:D27) -> 0 | E28: =B28-(C28+D28) -> 0 | F28: =SUM(F4:F27) -> 0 | G28: =E28-F28 -> 0 | H28: =G28/E28 -> #DIV/0! | I28: =SUM(I4:I27) -> 0 | J28: =G28-I28 -> 0 | K28: =J28/E28 -> #DIV/0!

Sheet Despesas 2026
A3: UNIDADE | B3: RECEITA BRUTA | C3: ISS/PIS/COFINS | D3: DEVOLUÇÕES | E3: RECEITA LIQUIDA | F3: CUSTOS / DESPESAS | G3: EBITDA | H3: MARGEM EBITDA | I3: IRPJ/CSLL | J3: LL | K3: MARGEM LIQUIDA
A4: ABC | B4: =SUM('Despesas JAN 2026'!B4,'Despesas FEV 2026'!B4,'Despesas MAR 2026'!B4,'Despesas ABR 2026'!B4,'Despesas MAI 2026'!B4,'Despesas JUN 2026'!B4,'Despesas JUL 2026'!B4,'Despesas AGO 2026'!B4,'Despesas SET 2026'!B4,'Despesas OUT 2026'!B4,'Despesas NOV 2026'!B4,'Despesas DEZ 2026'!B4) -> 579438 | C4: =SUM('Despesas JAN 2026'!C4,'Despesas FEV 2026'!C4,'Despesas MAR 2026'!C4,'Despesas ABR 2026'!C4,'Despesas MAI 2026'!C4,'Despesas JUN 2026'!C4,'Despesas JUL 2026'!C4,'Despesas AGO 2026'!C4,'Despesas SET 2026'!C4,'Despesas OUT 2026'!C4,'Despesas NOV 2026'!C4,'Despesas DEZ 2026'!C4) -> 31582.176 | D4: =SUM('Despesas JAN 2026'!D4,'Despesas FEV 2026'!D4,'Despesas MAR 2026'!D4,'Despesas ABR 2026'!D4,'Despesas MAI 2026'!D4,'Despesas JUN 2026'!D4,'Despesas JUL 2026'!D4,'Despesas AGO 2026'!D4,'Despesas SET 2026'!D4,'Despesas OUT 2026'!D4,'Despesas NOV 2026'!D4,'Despesas DEZ 2026'!D4) -> 0 | E4: =B4-(C4+D4) -> 547855.82 | F4: =SUM('Despesas JAN 2026'!F4,'Despesas FEV 2026'!F4,'Despesas MAR 2026'!F4,'Despesas ABR 2026'!F4,'Despesas MAI 2026'!F4,'Despesas JUN 2026'!F4,'Despesas JUL 2026'!F4,'Despesas AGO 2026'!F4,'Despesas SET 2026'!F4,'Despesas OUT 2026'!F4,'Despesas NOV 2026'!F4,'Despesas DEZ 2026'!F4) -> 257950.73 | G4: =E4-F4 -> 289905.09 | H4: =G4/E4 -> 0.52916311 | I4: =SUM('Despesas JAN 2026'!I4,'Despesas FEV 2026'!I4,'Despesas MAR 2026'!I4,'Despesas ABR 2026'!I4,'Despesas MAI 2026'!I4,'Despesas JUN 2026'!I4,'Despesas JUL 2026'!I4,'Despesas AGO 2026'!I4,'Despesas SET 2026'!I4,'Despesas OUT 2026'!I4,'Despesas NOV 2026'!I4,'Despesas DEZ 2026'!I4) -> 10228.4 | J4: =G4-I4 -> 279676.69 | K4: =J4/E4 -> 0.51049323
A5: Anália Franco | B5: =SUM('Despesas JAN 2026'!B5,'Despesas FEV 2026'!B5,'Despesas MAR 2026'!B5,'Despesas ABR 2026'!B5,'Despesas MAI 2026'!B5,'Despesas JUN 2026'!B5,'Despesas JUL 2026'!B5,'Despesas AGO 2026'!B5,'Despesas SET 2026'!B5,'Despesas OUT 2026'!B5,'Despesas NOV 2026'!B5,'Despesas DEZ 2026'!B5) -> 507186 | C5: =SUM('Despesas JAN 2026'!C5,'Despesas FEV 2026'!C5,'Despesas MAR 2026'!C5,'Despesas ABR 2026'!C5,'Despesas MAI 2026'!C5,'Despesas JUN 2026'!C5,'Despesas JUL 2026'!C5,'Despesas AGO 2026'!C5,'Despesas SET 2026'!C5,'Despesas OUT 2026'!C5,'Despesas NOV 2026'!C5,'Despesas DEZ 2026'!C5) -> 28770.88 | D5: =SUM('Despesas JAN 2026'!D5,'Despesas FEV 2026'!D5,'Despesas MAR 2026'!D5,'Despesas ABR 2026'!D5,'Despesas MAI 2026'!D5,'Despesas JUN 2026'!D5,'Despesas JUL 2026'!D5,'Despesas AGO 2026'!D5,'Despesas SET 2026'!D5,'Despesas OUT 2026'!D5,'Despesas NOV 2026'!D5,'Despesas DEZ 2026'!D5) -> 0 | E5: =B5-(C5+D5) -> 478415.12 | F5: =SUM('Despesas JAN 2026'!F5,'Despesas FEV 2026'!F5,'Despesas MAR 2026'!F5,'Despesas ABR 2026'!F5,'Despesas MAI 2026'!F5,'Despesas JUN 2026'!F5,'Despesas JUL 2026'!F5,'Despesas AGO 2026'!F5,'Despesas SET 2026'!F5,'Despesas OUT 2026'!F5,'Despesas NOV 2026'!F5,'Despesas DEZ 2026'!F5) -> 233914.11 | G5: =E5-F5 -> 244501.01 | H5: =G5/E5 -> 0.51106456 | I5: =SUM('Despesas JAN 2026'!I5,'Despesas FEV 2026'!I5,'Despesas MAR 2026'!I5,'Despesas ABR 2026'!I5,'Despesas MAI 2026'!I5,'Despesas JUN 2026'!I5,'Despesas JUL 2026'!I5,'Despesas AGO 2026'!I5,'Despesas SET 2026'!I5,'Despesas OUT 2026'!I5,'Despesas NOV 2026'!I5,'Despesas DEZ 2026'!I5) -> 10468.27 | J5: =G5-I5 -> 234032.74 | K5: =J5/E5 -> 0.48918341
A6: Belo Horizonte | B6: =SUM('Despesas JAN 2026'!B6,'Despesas FEV 2026'!B6,'Despesas MAR 2026'!B6,'Despesas ABR 2026'!B6,'Despesas MAI 2026'!B6,'Despesas JUN 2026'!B6,'Despesas JUL 2026'!B6,'Despesas AGO 2026'!B6,'Despesas SET 2026'!B6,'Despesas OUT 2026'!B6,'Despesas NOV 2026'!B6,'Despesas DEZ 2026'!B6) -> 1085749 | C6: =SUM('Despesas JAN 2026'!C6,'Despesas FEV 2026'!C6,'Despesas MAR 2026'!C6,'Despesas ABR 2026'!C6,'Despesas MAI 2026'!C6,'Despesas JUN 2026'!C6,'Despesas JUL 2026'!C6,'Despesas AGO 2026'!C6,'Despesas SET 2026'!C6,'Despesas OUT 2026'!C6,'Despesas NOV 2026'!C6,'Despesas DEZ 2026'!C6) -> 58463.52 | D6: =SUM('Despesas JAN 2026'!D6,'Despesas FEV 2026'!D6,'Despesas MAR 2026'!D6,'Despesas ABR 2026'!D6,'Despesas MAI 2026'!D6,'Despesas JUN 2026'!D6,'Despesas JUL 2026'!D6,'Despesas AGO 2026'!D6,'Despesas SET 2026'!D6,'Despesas OUT 2026'!D6,'Despesas NOV 2026'!D6,'Despesas DEZ 2026'!D6) -> 0 | E6: =B6-(C6+D6) -> 1027285.5 | F6: =SUM('Despesas JAN 2026'!F6,'Despesas FEV 2026'!F6,'Despesas MAR 2026'!F6,'Despesas ABR 2026'!F6,'Despesas MAI 2026'!F6,'Despesas JUN 2026'!F6,'Despesas JUL 2026'!F6,'Despesas AGO 2026'!F6,'Despesas SET 2026'!F6,'Despesas OUT 2026'!F6,'Despesas NOV 2026'!F6,'Despesas DEZ 2026'!F6) -> 645351.81 | G6: =E6-F6 -> 381933.67 | H6: =G6/E6 -> 0.37178922 | I6: =SUM('Despesas JAN 2026'!I6,'Despesas FEV 2026'!I6,'Despesas MAR 2026'!I6,'Despesas ABR 2026'!I6,'Despesas MAI 2026'!I6,'Despesas JUN 2026'!I6,'Despesas JUL 2026'!I6,'Despesas AGO 2026'!I6,'Despesas SET 2026'!I6,'Despesas OUT 2026'!I6,'Despesas NOV 2026'!I6,'Despesas DEZ 2026'!I6) -> 25755.13 | J6: =G6-I6 -> 356178.54 | K6: =J6/E6 -> 0.34671816
A7: Brasília | B7: =SUM('Despesas JAN 2026'!B7,'Despesas FEV 2026'!B7,'Despesas MAR 2026'!B7,'Despesas ABR 2026'!B7,'Despesas MAI 2026'!B7,'Despesas JUN 2026'!B7,'Despesas JUL 2026'!B7,'Despesas AGO 2026'!B7,'Despesas SET 2026'!B7,'Despesas OUT 2026'!B7,'Despesas NOV 2026'!B7,'Despesas DEZ 2026'!B7) -> 963304 | C7: =SUM('Despesas JAN 2026'!C7,'Despesas FEV 2026'!C7,'Despesas MAR 2026'!C7,'Despesas ABR 2026'!C7,'Despesas MAI 2026'!C7,'Despesas JUN 2026'!C7,'Despesas JUL 2026'!C7,'Despesas AGO 2026'!C7,'Despesas SET 2026'!C7,'Despesas OUT 2026'!C7,'Despesas NOV 2026'!C7,'Despesas DEZ 2026'!C7) -> 55651.02 | D7: =SUM('Despesas JAN 2026'!D7,'Despesas FEV 2026'!D7,'Despesas MAR 2026'!D7,'Despesas ABR 2026'!D7,'Despesas MAI 2026'!D7,'Despesas JUN 2026'!D7,'Despesas JUL 2026'!D7,'Despesas AGO 2026'!D7,'Despesas SET 2026'!D7,'Despesas OUT 2026'!D7,'Despesas NOV 2026'!D7,'Despesas DEZ 2026'!D7) -> 0 | E7: =B7-(C7+D7) -> 907652.98 | F7: =SUM('Despesas JAN 2026'!F7,'Despesas FEV 2026'!F7,'Despesas MAR 2026'!F7,'Despesas ABR 2026'!F7,'Despesas MAI 2026'!F7,'Despesas JUN 2026'!F7,'Despesas JUL 2026'!F7,'Despesas AGO 2026'!F7,'Despesas SET 2026'!F7,'Despesas OUT 2026'!F7,'Despesas NOV 2026'!F7,'Despesas DEZ 2026'!F7) -> 531881.27 | G7: =E7-F7 -> 375771.71 | H7: =G7/E7 -> 0.41400371 | I7: =SUM('Despesas JAN 2026'!I7,'Despesas FEV 2026'!I7,'Despesas MAR 2026'!I7,'Despesas ABR 2026'!I7,'Despesas MAI 2026'!I7,'Despesas JUN 2026'!I7,'Despesas JUL 2026'!I7,'Despesas AGO 2026'!I7,'Despesas SET 2026'!I7,'Despesas OUT 2026'!I7,'Despesas NOV 2026'!I7,'Despesas DEZ 2026'!I7) -> 23257.02 | J7: =G7-I7 -> 352514.69 | K7: =J7/E7 -> 0.38838046
A8: Campinas | B8: =SUM('Despesas JAN 2026'!B8,'Despesas FEV 2026'!B8,'Despesas MAR 2026'!B8,'Despesas ABR 2026'!B8,'Despesas MAI 2026'!B8,'Despesas JUN 2026'!B8,'Despesas JUL 2026'!B8,'Despesas AGO 2026'!B8,'Despesas SET 2026'!B8,'Despesas OUT 2026'!B8,'Despesas NOV 2026'!B8,'Despesas DEZ 2026'!B8) -> 866232 | C8: =SUM('Despesas JAN 2026'!C8,'Despesas FEV 2026'!C8,'Despesas MAR 2026'!C8,'Despesas ABR 2026'!C8,'Despesas MAI 2026'!C8,'Despesas JUN 2026'!C8,'Despesas JUL 2026'!C8,'Despesas AGO 2026'!C8,'Despesas SET 2026'!C8,'Despesas OUT 2026'!C8,'Despesas NOV 2026'!C8,'Despesas DEZ 2026'!C8) -> 57789.564 | D8: =SUM('Despesas JAN 2026'!D8,'Despesas FEV 2026'!D8,'Despesas MAR 2026'!D8,'Despesas ABR 2026'!D8,'Despesas MAI 2026'!D8,'Despesas JUN 2026'!D8,'Despesas JUL 2026'!D8,'Despesas AGO 2026'!D8,'Despesas SET 2026'!D8,'Despesas OUT 2026'!D8,'Despesas NOV 2026'!D8,'Despesas DEZ 2026'!D8) -> 0 | E8: =B8-(C8+D8) -> 808442.44 | F8: =SUM('Despesas JAN 2026'!F8,'Despesas FEV 2026'!F8,'Despesas MAR 2026'!F8,'Despesas ABR 2026'!F8,'Despesas MAI 2026'!F8,'Despesas JUN 2026'!F8,'Despesas JUL 2026'!F8,'Despesas AGO 2026'!F8,'Despesas SET 2026'!F8,'Despesas OUT 2026'!F8,'Despesas NOV 2026'!F8,'Despesas DEZ 2026'!F8) -> 598274.65 | G8: =E8-F8 -> 210167.79 | H8: =G8/E8 -> 0.2599663 | I8: =SUM('Despesas JAN 2026'!I8,'Despesas FEV 2026'!I8,'Despesas MAR 2026'!I8,'Despesas ABR 2026'!I8,'Despesas MAI 2026'!I8,'Despesas JUN 2026'!I8,'Despesas JUL 2026'!I8,'Despesas AGO 2026'!I8,'Despesas SET 2026'!I8,'Despesas OUT 2026'!I8,'Despesas NOV 2026'!I8,'Despesas DEZ 2026'!I8) -> 20049.32 | J8: =G8-I8 -> 190118.47 | K8: =J8/E8 -> 0.23516636
A9: Campo Grande | B9: =SUM('Despesas JAN 2026'!B9,'Despesas FEV 2026'!B9,'Despesas MAR 2026'!B9,'Despesas ABR 2026'!B9,'Despesas MAI 2026'!B9,'Despesas JUN 2026'!B9,'Despesas JUL 2026'!B9,'Despesas AGO 2026'!B9,'Despesas SET 2026'!B9,'Despesas OUT 2026'!B9,'Despesas NOV 2026'!B9,'Despesas DEZ 2026'!B9) -> 430274 | C9: =SUM('Despesas JAN 2026'!C9,'Despesas FEV 2026'!C9,'Despesas MAR 2026'!C9,'Despesas ABR 2026'!C9,'Despesas MAI 2026'!C9,'Despesas JUN 2026'!C9,'Despesas JUL 2026'!C9,'Despesas AGO 2026'!C9,'Despesas SET 2026'!C9,'Despesas OUT 2026'!C9,'Despesas NOV 2026'!C9,'Despesas DEZ 2026'!C9) -> 29025.903 | D9: =SUM('Despesas JAN 2026'!D9,'Despesas FEV 2026'!D9,'Despesas MAR 2026'!D9,'Despesas ABR 2026'!D9,'Despesas MAI 2026'!D9,'Despesas JUN 2026'!D9,'Despesas JUL 2026'!D9,'Despesas AGO 2026'!D9,'Despesas SET 2026'!D9,'Despesas OUT 2026'!D9,'Despesas NOV 2026'!D9,'Despesas DEZ 2026'!D9) -> 0 | E9: =B9-(C9+D9) -> 401248.1 | F9: =SUM('Despesas JAN 2026'!F9,'Despesas FEV 2026'!F9,'Despesas MAR 2026'!F9,'Despesas ABR 2026'!F9,'Despesas MAI 2026'!F9,'Despesas JUN 2026'!F9,'Despesas JUL 2026'!F9,'Despesas AGO 2026'!F9,'Despesas SET 2026'!F9,'Despesas OUT 2026'!F9,'Despesas NOV 2026'!F9,'Despesas DEZ 2026'!F9) -> 326602.78 | G9: =E9-F9 -> 74645.321 | H9: =G9/E9 -> 0.18603283 | I9: =SUM('Despesas JAN 2026'!I9,'Despesas FEV 2026'!I9,'Despesas MAR 2026'!I9,'Despesas ABR 2026'!I9,'Despesas MAI 2026'!I9,'Despesas JUN 2026'!I9,'Despesas JUL 2026'!I9,'Despesas AGO 2026'!I9,'Despesas SET 2026'!I9,'Despesas OUT 2026'!I9,'Despesas NOV 2026'!I9,'Despesas DEZ 2026'!I9) -> 9643.72 | J9: =G9-I9 -> 65001.601 | K9: =J9/E9 -> 0.16199853
A10: Curitiba | B10: =SUM('Despesas JAN 2026'!B10,'Despesas FEV 2026'!B10,'Despesas MAR 2026'!B10,'Despesas ABR 2026'!B10,'Despesas MAI 2026'!B10,'Despesas JUN 2026'!B10,'Despesas JUL 2026'!B10,'Despesas AGO 2026'!B10,'Despesas SET 2026'!B10,'Despesas OUT 2026'!B10,'Despesas NOV 2026'!B10,'Despesas DEZ 2026'!B10) -> 539665.58 | C10: =SUM('Despesas JAN 2026'!C10,'Despesas FEV 2026'!C10,'Despesas MAR 2026'!C10,'Despesas ABR 2026'!C10,'Despesas MAI 2026'!C10,'Despesas JUN 2026'!C10,'Despesas JUL 2026'!C10,'Despesas AGO 2026'!C10,'Despesas SET 2026'!C10,'Despesas OUT 2026'!C10,'Despesas NOV 2026'!C10,'Despesas DEZ 2026'!C10) -> 34310.321 | D10: =SUM('Despesas JAN 2026'!D10,'Despesas FEV 2026'!D10,'Despesas MAR 2026'!D10,'Despesas ABR 2026'!D10,'Despesas MAI 2026'!D10,'Despesas JUN 2026'!D10,'Despesas JUL 2026'!D10,'Despesas AGO 2026'!D10,'Despesas SET 2026'!D10,'Despesas OUT 2026'!D10,'Despesas NOV 2026'!D10,'Despesas DEZ 2026'!D10) -> 0 | E10: =B10-(C10+D10) -> 505355.26 | F10: =SUM('Despesas JAN 2026'!F10,'Despesas FEV 2026'!F10,'Despesas MAR 2026'!F10,'Despesas ABR 2026'!F10,'Despesas MAI 2026'!F10,'Despesas JUN 2026'!F10,'Despesas JUL 2026'!F10,'Despesas AGO 2026'!F10,'Despesas SET 2026'!F10,'Despesas OUT 2026'!F10,'Despesas NOV 2026'!F10,'Despesas DEZ 2026'!F10) -> 431427.3 | G10: =E10-F10 -> 73927.956 | H10: =G10/E10 -> 0.14628908 | I10: =SUM('Despesas JAN 2026'!I10,'Despesas FEV 2026'!I10,'Despesas MAR 2026'!I10,'Despesas ABR 2026'!I10,'Despesas MAI 2026'!I10,'Despesas JUN 2026'!I10,'Despesas JUL 2026'!I10,'Despesas AGO 2026'!I10,'Despesas SET 2026'!I10,'Despesas OUT 2026'!I10,'Despesas NOV 2026'!I10,'Despesas DEZ 2026'!I10) -> 8674.25 | J10: =G10-I10 -> 65253.706 | K10: =J10/E10 -> 0.12912442
A11: Florianópolis | B11: =SUM('Despesas JAN 2026'!B11,'Despesas FEV 2026'!B11,'Despesas MAR 2026'!B11,'Despesas ABR 2026'!B11,'Despesas MAI 2026'!B11,'Despesas JUN 2026'!B11,'Despesas JUL 2026'!B11,'Despesas AGO 2026'!B11,'Despesas SET 2026'!B11,'Despesas OUT 2026'!B11,'Despesas NOV 2026'!B11,'Despesas DEZ 2026'!B11) -> 112510 | C11: =SUM('Despesas JAN 2026'!C11,'Despesas FEV 2026'!C11,'Despesas MAR 2026'!C11,'Despesas ABR 2026'!C11,'Despesas MAI 2026'!C11,'Despesas JUN 2026'!C11,'Despesas JUL 2026'!C11,'Despesas AGO 2026'!C11,'Despesas SET 2026'!C11,'Despesas OUT 2026'!C11,'Despesas NOV 2026'!C11,'Despesas DEZ 2026'!C11) -> 16400.27 | D11: =SUM('Despesas JAN 2026'!D11,'Despesas FEV 2026'!D11,'Despesas MAR 2026'!D11,'Despesas ABR 2026'!D11,'Despesas MAI 2026'!D11,'Despesas JUN 2026'!D11,'Despesas JUL 2026'!D11,'Despesas AGO 2026'!D11,'Despesas SET 2026'!D11,'Despesas OUT 2026'!D11,'Despesas NOV 2026'!D11,'Despesas DEZ 2026'!D11) -> 0 | E11: =B11-(C11+D11) -> 96109.73 | F11: =SUM('Despesas JAN 2026'!F11,'Despesas FEV 2026'!F11,'Despesas MAR 2026'!F11,'Despesas ABR 2026'!F11,'Despesas MAI 2026'!F11,'Despesas JUN 2026'!F11,'Despesas JUL 2026'!F11,'Despesas AGO 2026'!F11,'Despesas SET 2026'!F11,'Despesas OUT 2026'!F11,'Despesas NOV 2026'!F11,'Despesas DEZ 2026'!F11) -> 187897.09 | G11: =E11-F11 -> -91787.357 | H11: =G11/E11 -> -0.95502669 | I11: =SUM('Despesas JAN 2026'!I11,'Despesas FEV 2026'!I11,'Despesas MAR 2026'!I11,'Despesas ABR 2026'!I11,'Despesas MAI 2026'!I11,'Despesas JUN 2026'!I11,'Despesas JUL 2026'!I11,'Despesas AGO 2026'!I11,'Despesas SET 2026'!I11,'Despesas OUT 2026'!I11,'Despesas NOV 2026'!I11,'Despesas DEZ 2026'!I11) -> 12706.39 | J11: =G11-I11 -> -104493.75 | K11: =J11/E11 -> -1.0872338
A12: Fortaleza | B12: =SUM('Despesas JAN 2026'!B12,'Despesas FEV 2026'!B12,'Despesas MAR 2026'!B12,'Despesas ABR 2026'!B12,'Despesas MAI 2026'!B12,'Despesas JUN 2026'!B12,'Despesas JUL 2026'!B12,'Despesas AGO 2026'!B12,'Despesas SET 2026'!B12,'Despesas OUT 2026'!B12,'Despesas NOV 2026'!B12,'Despesas DEZ 2026'!B12) -> 98428 | C12: =SUM('Despesas JAN 2026'!C12,'Despesas FEV 2026'!C12,'Despesas MAR 2026'!C12,'Despesas ABR 2026'!C12,'Despesas MAI 2026'!C12,'Despesas JUN 2026'!C12,'Despesas JUL 2026'!C12,'Despesas AGO 2026'!C12,'Despesas SET 2026'!C12,'Despesas OUT 2026'!C12,'Despesas NOV 2026'!C12,'Despesas DEZ 2026'!C12) -> 7779.059 | D12: =SUM('Despesas JAN 2026'!D12,'Despesas FEV 2026'!D12,'Despesas MAR 2026'!D12,'Despesas ABR 2026'!D12,'Despesas MAI 2026'!D12,'Despesas JUN 2026'!D12,'Despesas JUL 2026'!D12,'Despesas AGO 2026'!D12,'Despesas SET 2026'!D12,'Despesas OUT 2026'!D12,'Despesas NOV 2026'!D12,'Despesas DEZ 2026'!D12) -> 0 | E12: =B12-(C12+D12) -> 90648.941 | F12: =SUM('Despesas JAN 2026'!F12,'Despesas FEV 2026'!F12,'Despesas MAR 2026'!F12,'Despesas ABR 2026'!F12,'Despesas MAI 2026'!F12,'Despesas JUN 2026'!F12,'Despesas JUL 2026'!F12,'Despesas AGO 2026'!F12,'Despesas SET 2026'!F12,'Despesas OUT 2026'!F12,'Despesas NOV 2026'!F12,'Despesas DEZ 2026'!F12) -> 205730.87 | G12: =E12-F12 -> -115081.93 | H12: . | I12: =SUM('Despesas JAN 2026'!I12,'Despesas FEV 2026'!I12,'Despesas MAR 2026'!I12,'Despesas ABR 2026'!I12,'Despesas MAI 2026'!I12,'Despesas JUN 2026'!I12,'Despesas JUL 2026'!I12,'Despesas AGO 2026'!I12,'Despesas SET 2026'!I12,'Despesas OUT 2026'!I12,'Despesas NOV 2026'!I12,'Despesas DEZ 2026'!I12) -> 2826.33 | J12: =G12-I12 -> -117908.26 | K12: .
A13: Goiânia | B13: =SUM('Despesas JAN 2026'!B13,'Despesas FEV 2026'!B13,'Despesas MAR 2026'!B13,'Despesas ABR 2026'!B13,'Despesas MAI 2026'!B13,'Despesas JUN 2026'!B13,'Despesas JUL 2026'!B13,'Despesas AGO 2026'!B13,'Despesas SET 2026'!B13,'Despesas OUT 2026'!B13,'Despesas NOV 2026'!B13,'Despesas DEZ 2026'!B13) -> 695080 | C13: =SUM('Despesas JAN 2026'!C13,'Despesas FEV 2026'!C13,'Despesas MAR 2026'!C13,'Despesas ABR 2026'!C13,'Despesas MAI 2026'!C13,'Despesas JUN 2026'!C13,'Despesas JUL 2026'!C13,'Despesas AGO 2026'!C13,'Despesas SET 2026'!C13,'Despesas OUT 2026'!C13,'Despesas NOV 2026'!C13,'Despesas DEZ 2026'!C13) -> 42714.1 | D13: =SUM('Despesas JAN 2026'!D13,'Despesas FEV 2026'!D13,'Despesas MAR 2026'!D13,'Despesas ABR 2026'!D13,'Despesas MAI 2026'!D13,'Despesas JUN 2026'!D13,'Despesas JUL 2026'!D13,'Despesas AGO 2026'!D13,'Despesas SET 2026'!D13,'Despesas OUT 2026'!D13,'Despesas NOV 2026'!D13,'Despesas DEZ 2026'!D13) -> 0 | E13: =B13-(C13+D13) -> 652365.9 | F13: =SUM('Despesas JAN 2026'!F13,'Despesas FEV 2026'!F13,'Despesas MAR 2026'!F13,'Despesas ABR 2026'!F13,'Despesas MAI 2026'!F13,'Despesas JUN 2026'!F13,'Despesas JUL 2026'!F13,'Despesas AGO 2026'!F13,'Despesas SET 2026'!F13,'Despesas OUT 2026'!F13,'Despesas NOV 2026'!F13,'Despesas DEZ 2026'!F13) -> 499506.08 | G13: =E13-F13 -> 152859.82 | H13: =G13/E13 -> 0.23431608 | I13: =SUM('Despesas JAN 2026'!I13,'Despesas FEV 2026'!I13,'Despesas MAR 2026'!I13,'Despesas ABR 2026'!I13,'Despesas MAI 2026'!I13,'Despesas JUN 2026'!I13,'Despesas JUL 2026'!I13,'Despesas AGO 2026'!I13,'Despesas SET 2026'!I13,'Despesas OUT 2026'!I13,'Despesas NOV 2026'!I13,'Despesas DEZ 2026'!I13) -> 19344.9 | J13: =G13-I13 -> 133514.92 | K13: =J13/E13 -> 0.20466263
A14: Guarulhos | B14: =SUM('Despesas JAN 2026'!B14,'Despesas FEV 2026'!B14,'Despesas MAR 2026'!B14,'Despesas ABR 2026'!B14,'Despesas MAI 2026'!B14,'Despesas JUN 2026'!B14,'Despesas JUL 2026'!B14,'Despesas AGO 2026'!B14,'Despesas SET 2026'!B14,'Despesas OUT 2026'!B14,'Despesas NOV 2026'!B14,'Despesas DEZ 2026'!B14) -> 447182 | C14: =SUM('Despesas JAN 2026'!C14,'Despesas FEV 2026'!C14,'Despesas MAR 2026'!C14,'Despesas ABR 2026'!C14,'Despesas MAI 2026'!C14,'Despesas JUN 2026'!C14,'Despesas JUL 2026'!C14,'Despesas AGO 2026'!C14,'Despesas SET 2026'!C14,'Despesas OUT 2026'!C14,'Despesas NOV 2026'!C14,'Despesas DEZ 2026'!C14) -> 24619.475 | D14: =SUM('Despesas JAN 2026'!D14,'Despesas FEV 2026'!D14,'Despesas MAR 2026'!D14,'Despesas ABR 2026'!D14,'Despesas MAI 2026'!D14,'Despesas JUN 2026'!D14,'Despesas JUL 2026'!D14,'Despesas AGO 2026'!D14,'Despesas SET 2026'!D14,'Despesas OUT 2026'!D14,'Despesas NOV 2026'!D14,'Despesas DEZ 2026'!D14) -> 0 | E14: =B14-(C14+D14) -> 422562.53 | F14: =SUM('Despesas JAN 2026'!F14,'Despesas FEV 2026'!F14,'Despesas MAR 2026'!F14,'Despesas ABR 2026'!F14,'Despesas MAI 2026'!F14,'Despesas JUN 2026'!F14,'Despesas JUL 2026'!F14,'Despesas AGO 2026'!F14,'Despesas SET 2026'!F14,'Despesas OUT 2026'!F14,'Despesas NOV 2026'!F14,'Despesas DEZ 2026'!F14) -> 220669.69 | G14: =E14-F14 -> 201892.84 | H14: =G14/E14 -> 0.47778216 | I14: =SUM('Despesas JAN 2026'!I14,'Despesas FEV 2026'!I14,'Despesas MAR 2026'!I14,'Despesas ABR 2026'!I14,'Despesas MAI 2026'!I14,'Despesas JUN 2026'!I14,'Despesas JUL 2026'!I14,'Despesas AGO 2026'!I14,'Despesas SET 2026'!I14,'Despesas OUT 2026'!I14,'Despesas NOV 2026'!I14,'Despesas DEZ 2026'!I14) -> 11404.5 | J14: =G14-I14 -> 190488.34 | K14: =J14/E14 -> 0.45079325
A15: Itaim Bibi | B15: =SUM('Despesas JAN 2026'!B15,'Despesas FEV 2026'!B15,'Despesas MAR 2026'!B15,'Despesas ABR 2026'!B15,'Despesas MAI 2026'!B15,'Despesas JUN 2026'!B15,'Despesas JUL 2026'!B15,'Despesas AGO 2026'!B15,'Despesas SET 2026'!B15,'Despesas OUT 2026'!B15,'Despesas NOV 2026'!B15,'Despesas DEZ 2026'!B15) -> 1138954 | C15: =SUM('Despesas JAN 2026'!C15,'Despesas FEV 2026'!C15,'Despesas MAR 2026'!C15,'Despesas ABR 2026'!C15,'Despesas MAI 2026'!C15,'Despesas JUN 2026'!C15,'Despesas JUL 2026'!C15,'Despesas AGO 2026'!C15,'Despesas SET 2026'!C15,'Despesas OUT 2026'!C15,'Despesas NOV 2026'!C15,'Despesas DEZ 2026'!C15) -> 41377.906 | D15: =SUM('Despesas JAN 2026'!D15,'Despesas FEV 2026'!D15,'Despesas MAR 2026'!D15,'Despesas ABR 2026'!D15,'Despesas MAI 2026'!D15,'Despesas JUN 2026'!D15,'Despesas JUL 2026'!D15,'Despesas AGO 2026'!D15,'Despesas SET 2026'!D15,'Despesas OUT 2026'!D15,'Despesas NOV 2026'!D15,'Despesas DEZ 2026'!D15) -> 0 | E15: =B15-(C15+D15) -> 1097576.1 | F15: =SUM('Despesas JAN 2026'!F15,'Despesas FEV 2026'!F15,'Despesas MAR 2026'!F15,'Despesas ABR 2026'!F15,'Despesas MAI 2026'!F15,'Despesas JUN 2026'!F15,'Despesas JUL 2026'!F15,'Despesas AGO 2026'!F15,'Despesas SET 2026'!F15,'Despesas OUT 2026'!F15,'Despesas NOV 2026'!F15,'Despesas DEZ 2026'!F15) -> 886199.68 | G15: =E15-F15 -> 211376.42 | H15: =G15/E15 -> 0.19258475 | I15: =SUM('Despesas JAN 2026'!I15,'Despesas FEV 2026'!I15,'Despesas MAR 2026'!I15,'Despesas ABR 2026'!I15,'Despesas MAI 2026'!I15,'Despesas JUN 2026'!I15,'Despesas JUL 2026'!I15,'Despesas AGO 2026'!I15,'Despesas SET 2026'!I15,'Despesas OUT 2026'!I15,'Despesas NOV 2026'!I15,'Despesas DEZ 2026'!I15) -> 18285.4 | J15: =G15-I15 -> 193091.02 | K15: =J15/E15 -> 0.17592495
A16: Jundiaí | B16: =SUM('Despesas JAN 2026'!B16,'Despesas FEV 2026'!B16,'Despesas MAR 2026'!B16,'Despesas ABR 2026'!B16,'Despesas MAI 2026'!B16,'Despesas JUN 2026'!B16,'Despesas JUL 2026'!B16,'Despesas AGO 2026'!B16,'Despesas SET 2026'!B16,'Despesas OUT 2026'!B16,'Despesas NOV 2026'!B16,'Despesas DEZ 2026'!B16) -> 318260 | C16: =SUM('Despesas JAN 2026'!C16,'Despesas FEV 2026'!C16,'Despesas MAR 2026'!C16,'Despesas ABR 2026'!C16,'Despesas MAI 2026'!C16,'Despesas JUN 2026'!C16,'Despesas JUL 2026'!C16,'Despesas AGO 2026'!C16,'Despesas SET 2026'!C16,'Despesas OUT 2026'!C16,'Despesas NOV 2026'!C16,'Despesas DEZ 2026'!C16) -> 13307.85 | D16: =SUM('Despesas JAN 2026'!D16,'Despesas FEV 2026'!D16,'Despesas MAR 2026'!D16,'Despesas ABR 2026'!D16,'Despesas MAI 2026'!D16,'Despesas JUN 2026'!D16,'Despesas JUL 2026'!D16,'Despesas AGO 2026'!D16,'Despesas SET 2026'!D16,'Despesas OUT 2026'!D16,'Despesas NOV 2026'!D16,'Despesas DEZ 2026'!D16) -> 0 | E16: =B16-(C16+D16) -> 304952.15 | F16: =SUM('Despesas JAN 2026'!F16,'Despesas FEV 2026'!F16,'Despesas MAR 2026'!F16,'Despesas ABR 2026'!F16,'Despesas MAI 2026'!F16,'Despesas JUN 2026'!F16,'Despesas JUL 2026'!F16,'Despesas AGO 2026'!F16,'Despesas SET 2026'!F16,'Despesas OUT 2026'!F16,'Despesas NOV 2026'!F16,'Despesas DEZ 2026'!F16) -> 190499.18 | G16: =E16-F16 -> 114452.97 | H16: =G16/E16 -> 0.37531451 | I16: =SUM('Despesas JAN 2026'!I16,'Despesas FEV 2026'!I16,'Despesas MAR 2026'!I16,'Despesas ABR 2026'!I16,'Despesas MAI 2026'!I16,'Despesas JUN 2026'!I16,'Despesas JUL 2026'!I16,'Despesas AGO 2026'!I16,'Despesas SET 2026'!I16,'Despesas OUT 2026'!I16,'Despesas NOV 2026'!I16,'Despesas DEZ 2026'!I16) -> 8992.84 | J16: =G16-I16 -> 105460.13 | K16: =J16/E16 -> 0.34582516
A17: Manaus | B17: =SUM('Despesas JAN 2026'!B17,'Despesas FEV 2026'!B17,'Despesas MAR 2026'!B17,'Despesas ABR 2026'!B17,'Despesas MAI 2026'!B17,'Despesas JUN 2026'!B17,'Despesas JUL 2026'!B17,'Despesas AGO 2026'!B17,'Despesas SET 2026'!B17,'Despesas OUT 2026'!B17,'Despesas NOV 2026'!B17,'Despesas DEZ 2026'!B17) -> 0 | C17: =SUM('Despesas JAN 2026'!C17,'Despesas FEV 2026'!C17,'Despesas MAR 2026'!C17,'Despesas ABR 2026'!C17,'Despesas MAI 2026'!C17,'Despesas JUN 2026'!C17,'Despesas JUL 2026'!C17,'Despesas AGO 2026'!C17,'Despesas SET 2026'!C17,'Despesas OUT 2026'!C17,'Despesas NOV 2026'!C17,'Despesas DEZ 2026'!C17) -> 0 | D17: =SUM('Despesas JAN 2026'!D17,'Despesas FEV 2026'!D17,'Despesas MAR 2026'!D17,'Despesas ABR 2026'!D17,'Despesas MAI 2026'!D17,'Despesas JUN 2026'!D17,'Despesas JUL 2026'!D17,'Despesas AGO 2026'!D17,'Despesas SET 2026'!D17,'Despesas OUT 2026'!D17,'Despesas NOV 2026'!D17,'Despesas DEZ 2026'!D17) -> 0 | E17: =B17-(C17+D17) -> 0 | F17: =SUM('Despesas JAN 2026'!F17,'Despesas FEV 2026'!F17,'Despesas MAR 2026'!F17,'Despesas ABR 2026'!F17,'Despesas MAI 2026'!F17,'Despesas JUN 2026'!F17,'Despesas JUL 2026'!F17,'Despesas AGO 2026'!F17,'Despesas SET 2026'!F17,'Despesas OUT 2026'!F17,'Despesas NOV 2026'!F17,'Despesas DEZ 2026'!F17) -> 15180 | G17: =E17-F17 -> -15180 | H17: =G17/E17 -> #DIV/0! | I17: =SUM('Despesas JAN 2026'!I17,'Despesas FEV 2026'!I17,'Despesas MAR 2026'!I17,'Despesas ABR 2026'!I17,'Despesas MAI 2026'!I17,'Despesas JUN 2026'!I17,'Despesas JUL 2026'!I17,'Despesas AGO 2026'!I17,'Despesas SET 2026'!I17,'Despesas OUT 2026'!I17,'Despesas NOV 2026'!I17,'Despesas DEZ 2026'!I17) -> 407.9 | J17: =G17-I17 -> -15587.9 | K17: =J17/E17 -> #DIV/0!
A18: Piracicaba | B18: =SUM('Despesas JAN 2026'!B18,'Despesas FEV 2026'!B18,'Despesas MAR 2026'!B18,'Despesas ABR 2026'!B18,'Despesas MAI 2026'!B18,'Despesas JUN 2026'!B18,'Despesas JUL 2026'!B18,'Despesas AGO 2026'!B18,'Despesas SET 2026'!B18,'Despesas OUT 2026'!B18,'Despesas NOV 2026'!B18,'Despesas DEZ 2026'!B18) -> 256000 | C18: =SUM('Despesas JAN 2026'!C18,'Despesas FEV 2026'!C18,'Despesas MAR 2026'!C18,'Despesas ABR 2026'!C18,'Despesas MAI 2026'!C18,'Despesas JUN 2026'!C18,'Despesas JUL 2026'!C18,'Despesas AGO 2026'!C18,'Despesas SET 2026'!C18,'Despesas OUT 2026'!C18,'Despesas NOV 2026'!C18,'Despesas DEZ 2026'!C18) -> 14648.545 | D18: =SUM('Despesas JAN 2026'!D18,'Despesas FEV 2026'!D18,'Despesas MAR 2026'!D18,'Despesas ABR 2026'!D18,'Despesas MAI 2026'!D18,'Despesas JUN 2026'!D18,'Despesas JUL 2026'!D18,'Despesas AGO 2026'!D18,'Despesas SET 2026'!D18,'Despesas OUT 2026'!D18,'Despesas NOV 2026'!D18,'Despesas DEZ 2026'!D18) -> 0 | E18: =B18-(C18+D18) -> 241351.46 | F18: =SUM('Despesas JAN 2026'!F18,'Despesas FEV 2026'!F18,'Despesas MAR 2026'!F18,'Despesas ABR 2026'!F18,'Despesas MAI 2026'!F18,'Despesas JUN 2026'!F18,'Despesas JUL 2026'!F18,'Despesas AGO 2026'!F18,'Despesas SET 2026'!F18,'Despesas OUT 2026'!F18,'Despesas NOV 2026'!F18,'Despesas DEZ 2026'!F18) -> 158667.11 | G18: =E18-F18 -> 82684.345 | H18: =G18/E18 -> 0.34258896 | I18: =SUM('Despesas JAN 2026'!I18,'Despesas FEV 2026'!I18,'Despesas MAR 2026'!I18,'Despesas ABR 2026'!I18,'Despesas MAI 2026'!I18,'Despesas JUN 2026'!I18,'Despesas JUL 2026'!I18,'Despesas AGO 2026'!I18,'Despesas SET 2026'!I18,'Despesas OUT 2026'!I18,'Despesas NOV 2026'!I18,'Despesas DEZ 2026'!I18) -> 6007.63 | J18: =G18-I18 -> 76676.715 | K18: =J18/E18 -> 0.31769734
A19: Porto Alegre | B19: =SUM('Despesas JAN 2026'!B19,'Despesas FEV 2026'!B19,'Despesas MAR 2026'!B19,'Despesas ABR 2026'!B19,'Despesas MAI 2026'!B19,'Despesas JUN 2026'!B19,'Despesas JUL 2026'!B19,'Despesas AGO 2026'!B19,'Despesas SET 2026'!B19,'Despesas OUT 2026'!B19,'Despesas NOV 2026'!B19,'Despesas DEZ 2026'!B19) -> 642572 | C19: =SUM('Despesas JAN 2026'!C19,'Despesas FEV 2026'!C19,'Despesas MAR 2026'!C19,'Despesas ABR 2026'!C19,'Despesas MAI 2026'!C19,'Despesas JUN 2026'!C19,'Despesas JUL 2026'!C19,'Despesas AGO 2026'!C19,'Despesas SET 2026'!C19,'Despesas OUT 2026'!C19,'Despesas NOV 2026'!C19,'Despesas DEZ 2026'!C19) -> 22479.355 | D19: =SUM('Despesas JAN 2026'!D19,'Despesas FEV 2026'!D19,'Despesas MAR 2026'!D19,'Despesas ABR 2026'!D19,'Despesas MAI 2026'!D19,'Despesas JUN 2026'!D19,'Despesas JUL 2026'!D19,'Despesas AGO 2026'!D19,'Despesas SET 2026'!D19,'Despesas OUT 2026'!D19,'Despesas NOV 2026'!D19,'Despesas DEZ 2026'!D19) -> 0 | E19: =B19-(C19+D19) -> 620092.65 | F19: =SUM('Despesas JAN 2026'!F19,'Despesas FEV 2026'!F19,'Despesas MAR 2026'!F19,'Despesas ABR 2026'!F19,'Despesas MAI 2026'!F19,'Despesas JUN 2026'!F19,'Despesas JUL 2026'!F19,'Despesas AGO 2026'!F19,'Despesas SET 2026'!F19,'Despesas OUT 2026'!F19,'Despesas NOV 2026'!F19,'Despesas DEZ 2026'!F19) -> 453157.44 | G19: =E19-F19 -> 166935.21 | H19: =G19/E19 -> 0.26921011 | I19: =SUM('Despesas JAN 2026'!I19,'Despesas FEV 2026'!I19,'Despesas MAR 2026'!I19,'Despesas ABR 2026'!I19,'Despesas MAI 2026'!I19,'Despesas JUN 2026'!I19,'Despesas JUL 2026'!I19,'Despesas AGO 2026'!I19,'Despesas SET 2026'!I19,'Despesas OUT 2026'!I19,'Despesas NOV 2026'!I19,'Despesas DEZ 2026'!I19) -> 12721.07 | J19: =G19-I19 -> 154214.14 | K19: =J19/E19 -> 0.24869532
A20: Recife | B20: =SUM('Despesas JAN 2026'!B20,'Despesas FEV 2026'!B20,'Despesas MAR 2026'!B20,'Despesas ABR 2026'!B20,'Despesas MAI 2026'!B20,'Despesas JUN 2026'!B20,'Despesas JUL 2026'!B20,'Despesas AGO 2026'!B20,'Despesas SET 2026'!B20,'Despesas OUT 2026'!B20,'Despesas NOV 2026'!B20,'Despesas DEZ 2026'!B20) -> 568860 | C20: =SUM('Despesas JAN 2026'!C20,'Despesas FEV 2026'!C20,'Despesas MAR 2026'!C20,'Despesas ABR 2026'!C20,'Despesas MAI 2026'!C20,'Despesas JUN 2026'!C20,'Despesas JUL 2026'!C20,'Despesas AGO 2026'!C20,'Despesas SET 2026'!C20,'Despesas OUT 2026'!C20,'Despesas NOV 2026'!C20,'Despesas DEZ 2026'!C20) -> 26841.129 | D20: =SUM('Despesas JAN 2026'!D20,'Despesas FEV 2026'!D20,'Despesas MAR 2026'!D20,'Despesas ABR 2026'!D20,'Despesas MAI 2026'!D20,'Despesas JUN 2026'!D20,'Despesas JUL 2026'!D20,'Despesas AGO 2026'!D20,'Despesas SET 2026'!D20,'Despesas OUT 2026'!D20,'Despesas NOV 2026'!D20,'Despesas DEZ 2026'!D20) -> 0 | E20: =B20-(C20+D20) -> 542018.87 | F20: =SUM('Despesas JAN 2026'!F20,'Despesas FEV 2026'!F20,'Despesas MAR 2026'!F20,'Despesas ABR 2026'!F20,'Despesas MAI 2026'!F20,'Despesas JUN 2026'!F20,'Despesas JUL 2026'!F20,'Despesas AGO 2026'!F20,'Despesas SET 2026'!F20,'Despesas OUT 2026'!F20,'Despesas NOV 2026'!F20,'Despesas DEZ 2026'!F20) -> 405001.8 | G20: =E20-F20 -> 137017.07 | H20: =G20/E20 -> 0.25279022 | I20: =SUM('Despesas JAN 2026'!I20,'Despesas FEV 2026'!I20,'Despesas MAR 2026'!I20,'Despesas ABR 2026'!I20,'Despesas MAI 2026'!I20,'Despesas JUN 2026'!I20,'Despesas JUL 2026'!I20,'Despesas AGO 2026'!I20,'Despesas SET 2026'!I20,'Despesas OUT 2026'!I20,'Despesas NOV 2026'!I20,'Despesas DEZ 2026'!I20) -> 7939.03 | J20: =G20-I20 -> 129078.04 | K20: =J20/E20 -> 0.23814308
A21: Ribeirão Preto | B21: =SUM('Despesas JAN 2026'!B21,'Despesas FEV 2026'!B21,'Despesas MAR 2026'!B21,'Despesas ABR 2026'!B21,'Despesas MAI 2026'!B21,'Despesas JUN 2026'!B21,'Despesas JUL 2026'!B21,'Despesas AGO 2026'!B21,'Despesas SET 2026'!B21,'Despesas OUT 2026'!B21,'Despesas NOV 2026'!B21,'Despesas DEZ 2026'!B21) -> 1139700 | C21: =SUM('Despesas JAN 2026'!C21,'Despesas FEV 2026'!C21,'Despesas MAR 2026'!C21,'Despesas ABR 2026'!C21,'Despesas MAI 2026'!C21,'Despesas JUN 2026'!C21,'Despesas JUL 2026'!C21,'Despesas AGO 2026'!C21,'Despesas SET 2026'!C21,'Despesas OUT 2026'!C21,'Despesas NOV 2026'!C21,'Despesas DEZ 2026'!C21) -> 55289.16 | D21: =SUM('Despesas JAN 2026'!D21,'Despesas FEV 2026'!D21,'Despesas MAR 2026'!D21,'Despesas ABR 2026'!D21,'Despesas MAI 2026'!D21,'Despesas JUN 2026'!D21,'Despesas JUL 2026'!D21,'Despesas AGO 2026'!D21,'Despesas SET 2026'!D21,'Despesas OUT 2026'!D21,'Despesas NOV 2026'!D21,'Despesas DEZ 2026'!D21) -> 0 | E21: =B21-(C21+D21) -> 1084410.8 | F21: =SUM('Despesas JAN 2026'!F21,'Despesas FEV 2026'!F21,'Despesas MAR 2026'!F21,'Despesas ABR 2026'!F21,'Despesas MAI 2026'!F21,'Despesas JUN 2026'!F21,'Despesas JUL 2026'!F21,'Despesas AGO 2026'!F21,'Despesas SET 2026'!F21,'Despesas OUT 2026'!F21,'Despesas NOV 2026'!F21,'Despesas DEZ 2026'!F21) -> 638565.32 | G21: =E21-F21 -> 445845.52 | H21: =G21/E21 -> 0.41114078 | I21: =SUM('Despesas JAN 2026'!I21,'Despesas FEV 2026'!I21,'Despesas MAR 2026'!I21,'Despesas ABR 2026'!I21,'Despesas MAI 2026'!I21,'Despesas JUN 2026'!I21,'Despesas JUL 2026'!I21,'Despesas AGO 2026'!I21,'Despesas SET 2026'!I21,'Despesas OUT 2026'!I21,'Despesas NOV 2026'!I21,'Despesas DEZ 2026'!I21) -> 33429.44 | J21: =G21-I21 -> 412416.08 | K21: =J21/E21 -> 0.38031349
A22: Rio de Janeiro | B22: =SUM('Despesas JAN 2026'!B22,'Despesas FEV 2026'!B22,'Despesas MAR 2026'!B22,'Despesas ABR 2026'!B22,'Despesas MAI 2026'!B22,'Despesas JUN 2026'!B22,'Despesas JUL 2026'!B22,'Despesas AGO 2026'!B22,'Despesas SET 2026'!B22,'Despesas OUT 2026'!B22,'Despesas NOV 2026'!B22,'Despesas DEZ 2026'!B22) -> 415900 | C22: =SUM('Despesas JAN 2026'!C22,'Despesas FEV 2026'!C22,'Despesas MAR 2026'!C22,'Despesas ABR 2026'!C22,'Despesas MAI 2026'!C22,'Despesas JUN 2026'!C22,'Despesas JUL 2026'!C22,'Despesas AGO 2026'!C22,'Despesas SET 2026'!C22,'Despesas OUT 2026'!C22,'Despesas NOV 2026'!C22,'Despesas DEZ 2026'!C22) -> 30925.51 | D22: =SUM('Despesas JAN 2026'!D22,'Despesas FEV 2026'!D22,'Despesas MAR 2026'!D22,'Despesas ABR 2026'!D22,'Despesas MAI 2026'!D22,'Despesas JUN 2026'!D22,'Despesas JUL 2026'!D22,'Despesas AGO 2026'!D22,'Despesas SET 2026'!D22,'Despesas OUT 2026'!D22,'Despesas NOV 2026'!D22,'Despesas DEZ 2026'!D22) -> 0 | E22: =B22-(C22+D22) -> 384974.49 | F22: =SUM('Despesas JAN 2026'!F22,'Despesas FEV 2026'!F22,'Despesas MAR 2026'!F22,'Despesas ABR 2026'!F22,'Despesas MAI 2026'!F22,'Despesas JUN 2026'!F22,'Despesas JUL 2026'!F22,'Despesas AGO 2026'!F22,'Despesas SET 2026'!F22,'Despesas OUT 2026'!F22,'Despesas NOV 2026'!F22,'Despesas DEZ 2026'!F22) -> 404034.58 | G22: =E22-F22 -> -19060.086 | H22: =G22/E22 -> -0.049509997 | I22: =SUM('Despesas JAN 2026'!I22,'Despesas FEV 2026'!I22,'Despesas MAR 2026'!I22,'Despesas ABR 2026'!I22,'Despesas MAI 2026'!I22,'Despesas JUN 2026'!I22,'Despesas JUL 2026'!I22,'Despesas AGO 2026'!I22,'Despesas SET 2026'!I22,'Despesas OUT 2026'!I22,'Despesas NOV 2026'!I22,'Despesas DEZ 2026'!I22) -> 7538.24 | J22: =G22-I22 -> -26598.326 | K22: =J22/E22 -> -0.069091139
A23: Salvador | B23: =SUM('Despesas JAN 2026'!B23,'Despesas FEV 2026'!B23,'Despesas MAR 2026'!B23,'Despesas ABR 2026'!B23,'Despesas MAI 2026'!B23,'Despesas JUN 2026'!B23,'Despesas JUL 2026'!B23,'Despesas AGO 2026'!B23,'Despesas SET 2026'!B23,'Despesas OUT 2026'!B23,'Despesas NOV 2026'!B23,'Despesas DEZ 2026'!B23) -> 567032 | C23: =SUM('Despesas JAN 2026'!C23,'Despesas FEV 2026'!C23,'Despesas MAR 2026'!C23,'Despesas ABR 2026'!C23,'Despesas MAI 2026'!C23,'Despesas JUN 2026'!C23,'Despesas JUL 2026'!C23,'Despesas AGO 2026'!C23,'Despesas SET 2026'!C23,'Despesas OUT 2026'!C23,'Despesas NOV 2026'!C23,'Despesas DEZ 2026'!C23) -> 29522.81 | D23: =SUM('Despesas JAN 2026'!D23,'Despesas FEV 2026'!D23,'Despesas MAR 2026'!D23,'Despesas ABR 2026'!D23,'Despesas MAI 2026'!D23,'Despesas JUN 2026'!D23,'Despesas JUL 2026'!D23,'Despesas AGO 2026'!D23,'Despesas SET 2026'!D23,'Despesas OUT 2026'!D23,'Despesas NOV 2026'!D23,'Despesas DEZ 2026'!D23) -> 0 | E23: =B23-(C23+D23) -> 537509.19 | F23: =SUM('Despesas JAN 2026'!F23,'Despesas FEV 2026'!F23,'Despesas MAR 2026'!F23,'Despesas ABR 2026'!F23,'Despesas MAI 2026'!F23,'Despesas JUN 2026'!F23,'Despesas JUL 2026'!F23,'Despesas AGO 2026'!F23,'Despesas SET 2026'!F23,'Despesas OUT 2026'!F23,'Despesas NOV 2026'!F23,'Despesas DEZ 2026'!F23) -> 468852.95 | G23: =E23-F23 -> 68656.244 | H23: =G23/E23 -> 0.12773036 | I23: =SUM('Despesas JAN 2026'!I23,'Despesas FEV 2026'!I23,'Despesas MAR 2026'!I23,'Despesas ABR 2026'!I23,'Despesas MAI 2026'!I23,'Despesas JUN 2026'!I23,'Despesas JUL 2026'!I23,'Despesas AGO 2026'!I23,'Despesas SET 2026'!I23,'Despesas OUT 2026'!I23,'Despesas NOV 2026'!I23,'Despesas DEZ 2026'!I23) -> 9602.93 | J23: =G23-I23 -> 59053.314 | K23: =J23/E23 -> 0.10986475
A24: Santos | B24: =SUM('Despesas JAN 2026'!B24,'Despesas FEV 2026'!B24,'Despesas MAR 2026'!B24,'Despesas ABR 2026'!B24,'Despesas MAI 2026'!B24,'Despesas JUN 2026'!B24,'Despesas JUL 2026'!B24,'Despesas AGO 2026'!B24,'Despesas SET 2026'!B24,'Despesas OUT 2026'!B24,'Despesas NOV 2026'!B24,'Despesas DEZ 2026'!B24) -> 376792 | C24: =SUM('Despesas JAN 2026'!C24,'Despesas FEV 2026'!C24,'Despesas MAR 2026'!C24,'Despesas ABR 2026'!C24,'Despesas MAI 2026'!C24,'Despesas JUN 2026'!C24,'Despesas JUL 2026'!C24,'Despesas AGO 2026'!C24,'Despesas SET 2026'!C24,'Despesas OUT 2026'!C24,'Despesas NOV 2026'!C24,'Despesas DEZ 2026'!C24) -> 18628.603 | D24: =SUM('Despesas JAN 2026'!D24,'Despesas FEV 2026'!D24,'Despesas MAR 2026'!D24,'Despesas ABR 2026'!D24,'Despesas MAI 2026'!D24,'Despesas JUN 2026'!D24,'Despesas JUL 2026'!D24,'Despesas AGO 2026'!D24,'Despesas SET 2026'!D24,'Despesas OUT 2026'!D24,'Despesas NOV 2026'!D24,'Despesas DEZ 2026'!D24) -> 0 | E24: =B24-(C24+D24) -> 358163.4 | F24: =SUM('Despesas JAN 2026'!F24,'Despesas FEV 2026'!F24,'Despesas MAR 2026'!F24,'Despesas ABR 2026'!F24,'Despesas MAI 2026'!F24,'Despesas JUN 2026'!F24,'Despesas JUL 2026'!F24,'Despesas AGO 2026'!F24,'Despesas SET 2026'!F24,'Despesas OUT 2026'!F24,'Despesas NOV 2026'!F24,'Despesas DEZ 2026'!F24) -> 281048.05 | G24: =E24-F24 -> 77115.348 | H24: =G24/E24 -> 0.21530773 | I24: =SUM('Despesas JAN 2026'!I24,'Despesas FEV 2026'!I24,'Despesas MAR 2026'!I24,'Despesas ABR 2026'!I24,'Despesas MAI 2026'!I24,'Despesas JUN 2026'!I24,'Despesas JUL 2026'!I24,'Despesas AGO 2026'!I24,'Despesas SET 2026'!I24,'Despesas OUT 2026'!I24,'Despesas NOV 2026'!I24,'Despesas DEZ 2026'!I24) -> 14867.4 | J24: =G24-I24 -> 62247.948 | K24: =J24/E24 -> 0.17379763
... A27: Uberlândia | B27: =SUM('Despesas JAN 2026'!B27,'Despesas FEV 2026'!B27,'Despesas MAR 2026'!B27,'Despesas ABR 2026'!B27,'Despesas MAI 2026'!B27,'Despesas JUN 2026'!B27,'Despesas JUL 2026'!B27,'Despesas AGO 2026'!B27,'Despesas SET 2026'!B27,'Despesas OUT 2026'!B27,'Despesas NOV 2026'!B27,'Despesas DEZ 2026'!B27) -> 511680 | C27: =SUM('Despesas JAN 2026'!C27,'Despesas FEV 2026'!C27,'Despesas MAR 2026'!C27,'Despesas ABR 2026'!C27,'Despesas MAI 2026'!C27,'Despesas JUN 2026'!C27,'Despesas JUL 2026'!C27,'Despesas AGO 2026'!C27,'Despesas SET 2026'!C27,'Despesas OUT 2026'!C27,'Despesas NOV 2026'!C27,'Despesas DEZ 2026'!C27) -> 29395.82 | D27: =SUM('Despesas JAN 2026'!D27,'Despesas FEV 2026'!D27,'Despesas MAR 2026'!D27,'Despesas ABR 2026'!D27,'Despesas MAI 2026'!D27,'Despesas JUN 2026'!D27,'Despesas JUL 2026'!D27,'Despesas AGO 2026'!D27,'Despesas SET 2026'!D27,'Despesas OUT 2026'!D27,'Despesas NOV 2026'!D27,'Despesas DEZ 2026'!D27) -> 0 | E27: =B27-(C27+D27) -> 482284.18 | F27: =SUM('Despesas JAN 2026'!F27,'Despesas FEV 2026'!F27,'Despesas MAR 2026'!F27,'Despesas ABR 2026'!F27,'Despesas MAI 2026'!F27,'Despesas JUN 2026'!F27,'Despesas JUL 2026'!F27,'Despesas AGO 2026'!F27,'Despesas SET 2026'!F27,'Despesas OUT 2026'!F27,'Despesas NOV 2026'!F27,'Despesas DEZ 2026'!F27) -> 366277.46 | G27: =E27-F27 -> 116006.72 | H27: =G27/E27 -> 0.24053603 | I27: =SUM('Despesas JAN 2026'!I27,'Despesas FEV 2026'!I27,'Despesas MAR 2026'!I27,'Despesas ABR 2026'!I27,'Despesas MAI 2026'!I27,'Despesas JUN 2026'!I27,'Despesas JUL 2026'!I27,'Despesas AGO 2026'!I27,'Despesas SET 2026'!I27,'Despesas OUT 2026'!I27,'Despesas NOV 2026'!I27,'Despesas DEZ 2026'!I27) -> 16080.21 | J27: =G27-I27 -> 99926.513 | K27: =J27/E27 -> 0.20719426
A28: TOTAL | B28: =SUM(B4:B27) -> 13287698 | C28: =SUM(C4:C27) -> 713036.68 | D28: =SUM(D4:D27) -> 0 | E28: =B28-(C28+D28) -> 12574661 | F28: =SUM(F4:F27) -> 9008835.2 | G28: =E28-F28 -> 3565825.7 | H28: =G28/E28 -> 0.28357231 | I28: =SUM(I4:I27) -> 313490.37 | J28: =G28-I28 -> 3252335.3 | K28: =J28/E28 -> 0.25864199
